{
  "code": 200,
  "message": "成功",
  "data": {
    "id": "5924a75155b54278ac05f6bb",
    "name": "持松法师",
    "summary": "<p><b>持松法师</b>（1894年8月13日－1972年11月16日<sup class=\"sup-reference\" ref-id=\"ref-1\">[1]</sup>），法名<b>密林</b>，自号<b>师奘</b>沙门，其密法上师赐灌顶号<b>人入金刚</b><sup class=\"sup-reference\" ref-id=\"ref-2\">[2]</sup>，知名<a data-id=\"57c39acd0bd1be226ea0bda3\" data-type=\"entry\" href=\"/detail/57c39acd0bd1be226ea0bda3\" target=\"_blank\">佛教</a>僧侣。其学通显密，著作等身，以赴<a data-id=\"57c3f8010bd1be6b05a0bda3\" data-type=\"entry\" href=\"/detail/57c3f8010bd1be6b05a0bda3\" target=\"_blank\">日本</a>学<a data-id=\"5924279455b54278ac0107b1\" data-type=\"entry\" href=\"/detail/5924279455b54278ac0107b1\" target=\"_blank\">东密</a>、<a data-id=\"592412c455b54278ac000363\" data-type=\"entry\" href=\"/detail/592412c455b54278ac000363\" target=\"_blank\">台密</a>法，返华复兴<a data-id=\"59243c6155b54278ac01dc8a\" data-type=\"entry\" href=\"/detail/59243c6155b54278ac01dc8a\" target=\"_blank\">唐密</a>著称，世称显密圆融大宗师、唐密复兴初祖、贤密初祖。一说持松法师后已证果修得即身成佛，佛号&ldquo;松华如来&rdquo;。<sup class=\"sup-reference\" ref-id=\"ref-3\">[3]</sup>&nbsp;</p>\n",
    "imageId": "599f9ac71bc9226fdf61a235",
    "imageUrl": "//pic.allhistory.com/T15oDvByZT1RCvBVdK.jpg",
    "itemWeight": 0.0,
    "itemTag": null,
    "disambiguation": "",
    "relations": null,
    "relatedPoint": 1,
    "typePaths": [{
      "name": "宗教/宗教人物/佛教人物",
      "id": "2887"
    }],
    "categoryProp": 1,
    "birth": {
      "startTime": "1894-08-13 00:00:00",
      "timeDesc": null,
      "endTime": null,
      "startAccuracy": "0",
      "startNote": "",
      "endAccuracy": "0",
      "endNote": ""
    },
    "death": {
      "startTime": "1972-11-16 00:00:00",
      "timeDesc": null,
      "endTime": null,
      "startAccuracy": "0",
      "startNote": "",
      "endAccuracy": "0",
      "endNote": ""
    },
    "relationList": [{
      "id": "591065bc55b542257a03719a",
      "name": "张学良",
      "summary": "<p><b>张学良</b>（1901年6月3日－2001年10月15日<span id=\"noteTag-cite_ref-sup\"><sup class=\"sup-note\" note-id=\"note-1\">[注]</sup></span>），字<b>汉卿</b>，号<b>毅庵</b>，乳名<b>小六子</b>，真正小名<b>双喜</b><sup class=\"sup-reference\" ref-id=\"ref-1\">[1]</sup>，中国国民党<a data-id=\"591063bf55b542257a0341d7\" data-type=\"entry\" href=\"/detail/591063bf55b542257a0341d7\" target=\"_blank\">陆军</a><a data-id=\"592415b155b54278ac002890\" data-type=\"entry\" href=\"/detail/592415b155b54278ac002890\" target=\"_blank\">一级上将</a><sup class=\"sup-reference\" ref-id=\"ref-2\">[2]</sup>。中国<a data-id=\"5910687055b542257a03b1ed\" data-type=\"entry\" href=\"/detail/5910687055b542257a03b1ed\" target=\"_blank\">奉天省</a>（今<a data-id=\"591059cb55b542257a02517a\" data-type=\"entry\" href=\"/detail/591059cb55b542257a02517a\" target=\"_blank\">辽宁省</a>）<a data-id=\"591042e455b542257a002b23\" data-type=\"entry\" href=\"/detail/591042e455b542257a002b23\" target=\"_blank\">海城</a>人<sup class=\"sup-reference\" ref-id=\"ref-3\">[3]</sup>。生于<a data-id=\"591042f755b542257a002cca\" data-type=\"entry\" href=\"/detail/591042f755b542257a002cca\" target=\"_blank\">台安县</a>桑林，人称&ldquo;<b>少帅</b>&rdquo;，<a data-id=\"5924182755b54278ac004425\" data-type=\"entry\" href=\"/detail/5924182755b54278ac004425\" target=\"_blank\">奉系</a><a data-id=\"592415fb55b54278ac002c26\" data-type=\"entry\" href=\"/detail/592415fb55b54278ac002c26\" target=\"_blank\">军阀</a>领袖<a data-id=\"5910567d55b542257a020182\" data-type=\"entry\" href=\"/detail/5910567d55b542257a020182\" target=\"_blank\">张作霖</a>长子，&ldquo;<a data-id=\"5924171e55b54278ac0038c9\" data-type=\"entry\" href=\"/detail/5924171e55b54278ac0038c9\" target=\"_blank\">民国四公子</a>&rdquo;之一，享嵩寿100岁<sup class=\"sup-reference\" ref-id=\"ref-4\">[4]</sup>。</p>\n\n<p>1936年12月12日，<a data-id=\"5924150255b54278ac0020df\" data-type=\"entry\" href=\"/detail/5924150255b54278ac0020df\" target=\"_blank\">西安事变</a>爆发<sup class=\"sup-reference\" ref-id=\"ref-4\">[4]</sup>。张遭<a data-id=\"57ebd8df0bd1beb43a8b4567\" data-type=\"entry\" href=\"/detail/57ebd8df0bd1beb43a8b4567\" target=\"_blank\">蒋中正</a>、<a data-id=\"591065be55b542257a0371be\" data-type=\"entry\" href=\"/detail/591065be55b542257a0371be\" target=\"_blank\">蒋经国</a>父子<a data-id=\"592415b555b54278ac0028b9\" data-type=\"entry\" href=\"/detail/592415b555b54278ac0028b9\" target=\"_blank\">软禁</a>长达50余年，直到1990年，张才获得自由。张学良在台湾期间，先后曾居住于<a data-id=\"5910567255b542257a020096\" data-type=\"entry\" href=\"/detail/5910567255b542257a020096\" target=\"_blank\">高雄</a>寿山、<a data-id=\"5910567255b542257a020096\" data-type=\"entry\" href=\"/detail/5910567255b542257a020096\" target=\"_blank\">高雄</a><a data-id=\"5924150355b54278ac0020e9\" data-type=\"entry\" href=\"/detail/5924150355b54278ac0020e9\" target=\"_blank\">西子湾</a>、新竹五峰乡<a data-id=\"59241aaa55b54278ac0061d4\" data-type=\"entry\" href=\"/detail/59241aaa55b54278ac0061d4\" target=\"_blank\">清泉部落</a>。</p>\n",
      "imageId": "599f99621bc9226fdf6069e7",
      "imageUrl": "//pic.allhistory.com/T1rKWvBCWT1RCvBVdK.jpg",
      "itemWeight": 2.0091193,
      "itemTag": null,
      "disambiguation": "政府人物",
      "relations": {
        "direction": "<-",
        "id": "5b6153082a99a6000155bfcb",
        "relation": "结识",
        "relationDesc": "<div><a href=\"/detail/5910543755b542257a01cba6\" target=\"_blank\" style=\"font-weight: lighter;\">民国</a>十八年（1929年）夏，佛教大护法朱子桥居士，请<a href=\"/detail/5924a75155b54278ac05f6bb\" target=\"_blank\">持松法师</a>到<a href=\"/detail/591059cb55b542257a02517a\" target=\"_blank\">辽宁</a>作“仁王法会”。法会开始之日，东三省保安总司令<a href=\"/detail/591065bc55b542257a03719a\" target=\"_blank\">张学良</a>，偕<a href=\"/detail/591059cb55b542257a02517a\" target=\"_blank\">辽宁省</a>主席<a href=\"/detail/59244a5755b54278ac0280e8\" target=\"_blank\">翟文选</a>等人，入坛护摩受戒。</div>",
        "relationType": "CAREER",
        "relationTypeGroup": null,
        "relationWeight": 58,
        "relationId": "5b6153082a99a6000155bfcb",
        "time": {
          "startTime": "1929-00-00 00:00:00",
          "timeDesc": "",
          "endTime": "",
          "startAccuracy": null,
          "startNote": "",
          "endAccuracy": null,
          "endNote": ""
        },
        "position": [{
          "type": "Point",
          "coordinates": [122.995546882879, 40.9975196952698]
        }],
        "positionDesc": "辽宁省",
        "properties": null,
        "relationCategoryGroup": "HUMAN_HUMAN",
        "scoreMachine": null
      },
      "relatedPoint": 1,
      "typePaths": [{
        "name": "军事/军事人物/将领及首脑",
        "id": "2969"
      }],
      "categoryProp": null,
      "birth": {
        "startTime": "1901-06-03 00:00:00",
        "timeDesc": "",
        "endTime": null,
        "startAccuracy": "0",
        "startNote": "",
        "endAccuracy": "0",
        "endNote": ""
      },
      "death": {
        "startTime": "2001-10-15 00:00:00",
        "timeDesc": "",
        "endTime": null,
        "startAccuracy": "0",
        "startNote": "",
        "endAccuracy": "0",
        "endNote": ""
      },
      "relationList": null,
      "priorRelationTypes": null,
      "workType": null,
      "workIds": null,
      "auditing": false
    }, {
      "id": "59241e1355b54278ac008d14",
      "name": "高楠顺次郎",
      "summary": "<div class=\"mw-content-ltr\" dir=\"ltr\" id=\"mw-content-text\" lang=\"zh-CN\"><div class=\"mw-parser-output\"><div class=\"thumb tright\">\n</div>\n<p><b>高楠 顺次郎</b>（1866年6月29日－1945年6月28日），生于日本<a data-id=\"591063db55b542257a034477\" data-type=\"entry\" href=\"/detail/591063db55b542257a034477\" target=\"_blank\">广岛县</a><a data-id=\"59105fa055b542257a02dcec\" data-type=\"entry\" href=\"/detail/59105fa055b542257a02dcec\" target=\"_blank\">御调郡</a>八幡村字篝（现<a data-id=\"5910689055b542257a03b4bb\" data-type=\"entry\" href=\"/detail/5910689055b542257a03b4bb\" target=\"_blank\">三原市</a>），<a data-id=\"57c39acd0bd1be226ea0bda3\" data-type=\"entry\" href=\"/detail/57c39acd0bd1be226ea0bda3\" target=\"_blank\">佛教</a>学者与教育学者，为日本最早进行<a data-id=\"5910638255b542257a033c7d\" data-type=\"entry\" href=\"/detail/5910638255b542257a033c7d\" target=\"_blank\">梵文</a>研究佛教学者之一，将现代<a data-id=\"5924692655b54278ac040588\" data-type=\"entry\" href=\"/detail/5924692655b54278ac040588\" target=\"_blank\">佛教研究</a>引进日本。对于<a data-id=\"58841eb5bf6928014d909f3e\" data-type=\"entry\" href=\"/detail/58841eb5bf6928014d909f3e\" target=\"_blank\">印度哲学</a>与<a data-id=\"57c39acd0bd1be226ea0bda3\" data-type=\"entry\" href=\"/detail/57c39acd0bd1be226ea0bda3\" target=\"_blank\">佛教</a>在日本的发展有很大贡献，其中最大的成就为刊印<a data-id=\"59241e1355b54278ac008d15\" data-type=\"entry\" href=\"/detail/59241e1355b54278ac008d15\" target=\"_blank\">大正新修大藏经</a>100卷，此版本大藏经为目前学术界应用较广之大藏经。</p>\n</div></div>",
      "imageId": "59e8d0de7f1d597bc1d6de61",
      "imageUrl": "//pic.allhistory.com/T1YcEvBgxT1RCvBVdK.jpg",
      "itemWeight": 1.1528045,
      "itemTag": null,
      "disambiguation": "",
      "relations": {
        "direction": "->",
        "id": "5b6152702a99a6000155bf41",
        "relation": "结识",
        "relationDesc": "<div><div><a href=\"/detail/5910543755b542257a01cba6\" target=\"_blank\" style=\"font-weight: lighter;\">民国</a>十四年（1925年）冬，东亚佛教大会于<a href=\"/detail/582acec705c3fb164f030575\" target=\"_blank\">东京</a>举办，持松法师参加中国佛教代表团出席。在大会中他被选为教义研究部理事，并结识佛教学者<a href=\"/detail/5924990155b54278ac05428e\" target=\"_blank\">木村泰贤</a>、<a href=\"/detail/59241e1355b54278ac008d14\" target=\"_blank\">高楠顺次郎</a>、渡边海旭等。</div></div>",
        "relationType": "CAREER",
        "relationTypeGroup": null,
        "relationWeight": 5,
        "relationId": "5b6152702a99a6000155bf41",
        "time": {
          "startTime": "1925-00-00 00:00:00",
          "timeDesc": "",
          "endTime": "",
          "startAccuracy": null,
          "startNote": "",
          "endAccuracy": null,
          "endNote": ""
        },
        "position": [{
          "type": "Point",
          "coordinates": [139.758966680545, 35.6828377956761]
        }],
        "positionDesc": "东京",
        "properties": null,
        "relationCategoryGroup": "HUMAN_HUMAN",
        "scoreMachine": null
      },
      "relatedPoint": 1,
      "typePaths": [{
        "name": "社会生活/社会人物",
        "id": "2958"
      }],
      "categoryProp": null,
      "birth": {
        "startTime": "1866-00-00 00:00:00",
        "timeDesc": null,
        "endTime": null,
        "startAccuracy": "0",
        "startNote": "",
        "endAccuracy": "0",
        "endNote": ""
      },
      "death": {
        "startTime": "1945-06-28 00:00:00",
        "timeDesc": null,
        "endTime": null,
        "startAccuracy": "0",
        "startNote": "",
        "endAccuracy": "0",
        "endNote": ""
      },
      "relationList": null,
      "priorRelationTypes": null,
      "workType": null,
      "workIds": null,
      "auditing": false
    }, {
      "id": "5924990155b54278ac05428e",
      "name": "木村泰贤",
      "summary": "<div class=\"mw-content-ltr\" dir=\"ltr\" id=\"mw-content-text\" lang=\"zh-CN\"><div class=\"mw-parser-output\"><p><b>木村 泰贤</b>（1881年8月11日－1930年5月16日），生于<a data-id=\"57c3f8010bd1be6b05a0bda3\" data-type=\"entry\" href=\"/detail/57c3f8010bd1be6b05a0bda3\" target=\"_blank\">日本</a><a data-id=\"591063da55b542257a034460\" data-type=\"entry\" href=\"/detail/591063da55b542257a034460\" target=\"_blank\">岩手县</a>，日本<a data-id=\"59241c1455b54278ac0073e3\" data-type=\"entry\" href=\"/detail/59241c1455b54278ac0073e3\" target=\"_blank\">曹洞宗</a>僧侣，为岩手县东慈寺住持。佛教学者，<a data-id=\"5832ce6a05c3fb0d32ed4b9c\" data-type=\"entry\" href=\"/detail/5832ce6a05c3fb0d32ed4b9c\" target=\"_blank\">东京帝国大学</a>文学博士与教授。</p>\n</div></div>",
      "imageId": "",
      "imageUrl": "",
      "itemWeight": 0.36679268,
      "itemTag": null,
      "disambiguation": "",
      "relations": {
        "direction": "->",
        "id": "5b6152272a99a6000155bf3d",
        "relation": "结识",
        "relationDesc": "<div><a href=\"/detail/5910543755b542257a01cba6\" target=\"_blank\" style=\"font-weight: lighter;\">民国</a>十四年（1925年）冬，东亚佛教大会于<a href=\"/detail/582acec705c3fb164f030575\" target=\"_blank\">东京</a>举办，持松法师参加中国佛教代表团出席。在大会中他被选为教义研究部理事，并结识佛教学者<a href=\"/detail/5924990155b54278ac05428e\" target=\"_blank\">木村泰贤</a>、<a href=\"/detail/59241e1355b54278ac008d14\" target=\"_blank\">高楠顺次郎</a>、渡边海旭等。</div>",
        "relationType": "CAREER",
        "relationTypeGroup": null,
        "relationWeight": 42,
        "relationId": "5b6152272a99a6000155bf3d",
        "time": {
          "startTime": "1925-00-00 00:00:00",
          "timeDesc": "",
          "endTime": "",
          "startAccuracy": null,
          "startNote": "",
          "endAccuracy": null,
          "endNote": ""
        },
        "position": [{
          "type": "Point",
          "coordinates": [114.347203784083, 34.7961105957526]
        }, {
          "type": "Point",
          "coordinates": [139.758966680545, 35.6828377956761]
        }],
        "positionDesc": "东京",
        "properties": null,
        "relationCategoryGroup": "HUMAN_HUMAN",
        "scoreMachine": null
      },
      "relatedPoint": 1,
      "typePaths": [{
        "name": "社会生活/社会人物",
        "id": "2958"
      }],
      "categoryProp": null,
      "birth": {
        "startTime": "1881-08-11 00:00:00",
        "timeDesc": null,
        "endTime": null,
        "startAccuracy": "0",
        "startNote": "",
        "endAccuracy": "0",
        "endNote": ""
      },
      "death": {
        "startTime": "1930-05-16 00:00:00",
        "timeDesc": null,
        "endTime": null,
        "startAccuracy": "0",
        "startNote": "",
        "endAccuracy": "0",
        "endNote": ""
      },
      "relationList": null,
      "priorRelationTypes": null,
      "workType": null,
      "workIds": null,
      "auditing": false
    }, {
      "id": "59105bb955b542257a027f1b",
      "name": "吴佩孚",
      "summary": "<p><b>吴佩孚</b>（1874年4月22日－1939年12月4日），字<b>子玉</b>，<a data-id=\"5910579855b542257a021c44\" data-type=\"entry\" href=\"/detail/5910579855b542257a021c44\" target=\"_blank\">山东省</a><a data-id=\"591042d055b542257a002989\" data-type=\"entry\" href=\"/detail/591042d055b542257a002989\" target=\"_blank\">蓬莱县</a>人。晚清<a data-id=\"58326f2405c3fb6c7ded4ba1\" data-type=\"entry\" href=\"/detail/58326f2405c3fb6c7ded4ba1\" target=\"_blank\">秀才</a>，<a data-id=\"592415f855b54278ac002c05\" data-type=\"entry\" href=\"/detail/592415f855b54278ac002c05\" target=\"_blank\">北洋军阀</a>中曾经为实力最雄厚的<a data-id=\"5924169455b54278ac00327a\" data-type=\"entry\" href=\"/detail/5924169455b54278ac00327a\" target=\"_blank\">军阀</a>之一，并担任<a data-id=\"592415ca55b54278ac0029c7\" data-type=\"entry\" href=\"/detail/592415ca55b54278ac0029c7\" target=\"_blank\">直系军阀</a>的首领，官至<a data-id=\"58f883f355b54258e70009ac\" data-type=\"entry\" href=\"/detail/58f883f355b54258e70009ac\" target=\"_blank\">直</a><a data-id=\"5910579855b542257a021c44\" data-type=\"entry\" href=\"/detail/5910579855b542257a021c44\" target=\"_blank\">鲁</a><a data-id=\"5910579855b542257a021c41\" data-type=\"entry\" href=\"/detail/5910579855b542257a021c41\" target=\"_blank\">豫</a><a data-id=\"5924552655b54278ac02fccf\" data-type=\"entry\" href=\"/detail/5924552655b54278ac02fccf\" target=\"_blank\">巡阅使</a>。</p>\n",
      "imageId": "599f98d51bc9226fdf5fdbf3",
      "imageUrl": "//pic.allhistory.com/T1VAWvBCAT1RCvBVdK.jpg",
      "itemWeight": 1.6668315,
      "itemTag": null,
      "disambiguation": "",
      "relations": {
        "direction": "<->",
        "id": "5b6151752a99a6000155bf28",
        "relation": "其他",
        "relationDesc": "<div><a href=\"/detail/5910543755b542257a01cba6\" target=\"_blank\" style=\"font-weight: lighter;\">民国</a>十四年（1925年），北洋直系军阀<a href=\"/detail/59105bb955b542257a027f1b\" target=\"_blank\">吴佩孚</a>久闻《金刚经》之名，而不知其义。闻得持松法师在武汉弘化，特命幕僚礼请法师到府，为他讲解<a href=\"/detail/592416a855b54278ac003366\" target=\"_blank\">《金刚经》</a>。</div>",
        "relationType": "OTHER",
        "relationTypeGroup": "HUMAN_HUMAN",
        "relationWeight": 51,
        "relationId": "5b6151752a99a6000155bf28",
        "time": {
          "startTime": "1925-00-00 00:00:00",
          "timeDesc": "",
          "endTime": "",
          "startAccuracy": null,
          "startNote": "",
          "endAccuracy": null,
          "endNote": ""
        },
        "position": [{
          "type": "Point",
          "coordinates": [114.299279584089, 30.5960212961461]
        }],
        "positionDesc": "武汉市",
        "properties": null,
        "relationCategoryGroup": "HUMAN_HUMAN",
        "scoreMachine": null
      },
      "relatedPoint": 1,
      "typePaths": [{
        "name": "政治/政治人物/官员",
        "id": "2895"
      }],
      "categoryProp": null,
      "birth": {
        "startTime": "1878-04-22 00:00:00",
        "timeDesc": null,
        "endTime": null,
        "startAccuracy": "0",
        "startNote": "",
        "endAccuracy": "0",
        "endNote": ""
      },
      "death": {
        "startTime": "1939-12-04 00:00:00",
        "timeDesc": null,
        "endTime": null,
        "startAccuracy": "0",
        "startNote": "",
        "endAccuracy": "0",
        "endNote": ""
      },
      "relationList": null,
      "priorRelationTypes": null,
      "workType": null,
      "workIds": null,
      "auditing": false
    }, {
      "id": "57c3f8010bd1be6b05a0bda3",
      "name": "日本",
      "summary": "<p><b>日本国</b>（<span style=\"font-weight:normal\"><a data-id=\"5910619d55b542257a030d33\" data-type=\"entry\" href=\"/detail/5910619d55b542257a030d33\" target=\"_blank\">日语</a>：<span><span>日本国</span></span><small>／</small><span><span>にっぽんこく／にほんこく</span></span>&nbsp;<i><span class=\"Unicode\" style=\"white-space:normal; text-decoration: none\"><sup>Nippon-koku／Nihon-koku</sup></span></i>&nbsp;<small><a data-id=\"59105dd355b542257a02b0b6\" data-type=\"entry\" href=\"/detail/59105dd355b542257a02b0b6\" target=\"_blank\"><span style=\"font: bold sans-serif; text-decoration: none;\"><sup>?</sup></span></a></small></span>），通称<b>日本</b>，为位于<a data-id=\"5910434855b542257a0033b4\" data-type=\"entry\" href=\"/detail/5910434855b542257a0033b4\" target=\"_blank\">东亚</a>的<a data-id=\"5924145255b54278ac0018ad\" data-type=\"entry\" href=\"/detail/5924145255b54278ac0018ad\" target=\"_blank\">岛屿国家</a>，由<a data-id=\"5924206c55b54278ac00a9d8\" data-type=\"entry\" href=\"/detail/5924206c55b54278ac00a9d8\" target=\"_blank\">日本列岛</a>、<a data-id=\"5910664a55b542257a037e4b\" data-type=\"entry\" href=\"/detail/5910664a55b542257a037e4b\" target=\"_blank\">琉球群岛</a>和<a data-id=\"592420c555b54278ac00aea6\" data-type=\"entry\" href=\"/detail/592420c555b54278ac00aea6\" target=\"_blank\">伊豆</a>－<a data-id=\"592420c555b54278ac00aea9\" data-type=\"entry\" href=\"/detail/592420c555b54278ac00aea9\" target=\"_blank\">小笠原群岛</a>等6,852个岛屿组成<sup class=\"sup-reference\" ref-id=\"ref-11\">[11]</sup>，面积约37.8万平方公里<sup class=\"sup-reference\" ref-id=\"ref-12\">[12]</sup>。国土全境被<a data-id=\"592412af55b54278ac000285\" data-type=\"entry\" href=\"/detail/592412af55b54278ac000285\" target=\"_blank\">太平洋</a>及其<a data-id=\"5924214d55b54278ac00b5f8\" data-type=\"entry\" href=\"/detail/5924214d55b54278ac00b5f8\" target=\"_blank\">缘海</a>环抱，西邻<a data-id=\"58f8839b55b54258e70000c7\" data-type=\"entry\" href=\"/detail/58f8839b55b54258e70000c7\" target=\"_blank\">朝鲜半岛</a>及中国东北，北面<a data-id=\"59241cda55b54278ac007d3f\" data-type=\"entry\" href=\"/detail/59241cda55b54278ac007d3f\" target=\"_blank\">堪察加半岛</a>，西南为中国华南地区。<a data-id=\"5924291d55b54278ac011c0a\" data-type=\"entry\" href=\"/detail/5924291d55b54278ac011c0a\" target=\"_blank\">人口</a>达1.26亿<sup class=\"sup-reference\" ref-id=\"ref-7\">[7]</sup>，当中逾3,500万以上的人口居住于<a data-id=\"5924372d55b54278ac01c431\" data-type=\"entry\" href=\"/detail/5924372d55b54278ac01c431\" target=\"_blank\">首都</a><a data-id=\"5910434a55b542257a0033c8\" data-type=\"entry\" href=\"/detail/5910434a55b542257a0033c8\" target=\"_blank\">东京都</a>与周边数<a data-id=\"5924128d55b54278ac0000f1\" data-type=\"entry\" href=\"/detail/5924128d55b54278ac0000f1\" target=\"_blank\">县</a>构成的<a data-id=\"592439e755b54278ac01ca9e\" data-type=\"entry\" href=\"/detail/592439e755b54278ac01ca9e\" target=\"_blank\">首都圈</a>，为世界最大的<a data-id=\"59241ab455b54278ac0062af\" data-type=\"entry\" href=\"/detail/59241ab455b54278ac0062af\" target=\"_blank\">都市圈</a><sup class=\"sup-reference\" ref-id=\"ref-13\">[13]</sup>。<a data-id=\"5924145355b54278ac0018bc\" data-type=\"entry\" href=\"/detail/5924145355b54278ac0018bc\" target=\"_blank\">政体</a>施行<a data-id=\"59249bc955b54278ac05669b\" data-type=\"entry\" href=\"/detail/59249bc955b54278ac05669b\" target=\"_blank\">议会制君主立宪制</a>，君主<a data-id=\"582ace0d05c3fb234e030575\" data-type=\"entry\" href=\"/detail/582ace0d05c3fb234e030575\" target=\"_blank\">天皇</a>为日本国家与国民的<a data-id=\"592452bb55b54278ac02e251\" data-type=\"entry\" href=\"/detail/592452bb55b54278ac02e251\" target=\"_blank\">象征</a>，实际的<a data-id=\"5924248d55b54278ac00e133\" data-type=\"entry\" href=\"/detail/5924248d55b54278ac00e133\" target=\"_blank\">政治权力</a>则由<a data-id=\"5910542c55b542257a01cab3\" data-type=\"entry\" href=\"/detail/5910542c55b542257a01cab3\" target=\"_blank\">国会</a>、以及<a data-id=\"582ac81b05c3fb3f4d030571\" data-type=\"entry\" href=\"/detail/582ac81b05c3fb3f4d030571\" target=\"_blank\">首相</a>所领导的<a data-id=\"592421bd55b54278ac00bc6a\" data-type=\"entry\" href=\"/detail/592421bd55b54278ac00bc6a\" target=\"_blank\">内阁</a>掌理<sup class=\"sup-reference\" ref-id=\"ref-14\">[14]</sup>。</p>\n\n<p>传说日本于公元前660年2月11日建国<sup class=\"sup-reference\" ref-id=\"ref-15\">[15]</sup>，在公元4世纪出现<a data-id=\"592412f855b54278ac0005a8\" data-type=\"entry\" href=\"/detail/592412f855b54278ac0005a8\" target=\"_blank\">首个统一政权</a>，并于<a data-id=\"592417dc55b54278ac0040d2\" data-type=\"entry\" href=\"/detail/592417dc55b54278ac0040d2\" target=\"_blank\">大化改新</a>中确立了<a data-id=\"582ace0d05c3fb234e030575\" data-type=\"entry\" href=\"/detail/582ace0d05c3fb234e030575\" target=\"_blank\">天皇</a>的<a data-id=\"592416f955b54278ac00372a\" data-type=\"entry\" href=\"/detail/592416f955b54278ac00372a\" target=\"_blank\">中央集权</a>体制。12世纪后的六百年间，日本由<a data-id=\"5924373b55b54278ac01c4bb\" data-type=\"entry\" href=\"/detail/5924373b55b54278ac01c4bb\" target=\"_blank\">武家</a>阶级创建的<a data-id=\"5924240355b54278ac00da24\" data-type=\"entry\" href=\"/detail/5924240355b54278ac00da24\" target=\"_blank\">幕府</a>以天皇之名实际掌权。17世纪起因为锁国令的颁布，导致日本民间与外界的交流几近断绝，社会愈发封闭。1853年，<a data-id=\"57e1fc970bd1be9240524e5e\" data-type=\"entry\" href=\"/detail/57e1fc970bd1be9240524e5e\" target=\"_blank\">美国</a>海军将领<a data-id=\"5910610e55b542257a030065\" data-type=\"entry\" href=\"/detail/5910610e55b542257a030065\" target=\"_blank\">马休&middot;佩里</a>率军舰驶入<a data-id=\"592421ec55b54278ac00bf84\" data-type=\"entry\" href=\"/detail/592421ec55b54278ac00bf84\" target=\"_blank\">江户湾</a>递交美国总统国书，使<a data-id=\"59104cb055b542257a011b24\" data-type=\"entry\" href=\"/detail/59104cb055b542257a011b24\" target=\"_blank\">江户幕府</a>解除禁止诸藩建造大船的禁令，史称<a data-id=\"58f8842e55b54258e7000ee1\" data-type=\"entry\" href=\"/detail/58f8842e55b54258e7000ee1\" target=\"_blank\">黑船来航</a>。1867年江户幕府<a data-id=\"59241f0a55b54278ac009b61\" data-type=\"entry\" href=\"/detail/59241f0a55b54278ac009b61\" target=\"_blank\">大政奉还</a>，由<a data-id=\"582ace7405c3fb3853030571\" data-type=\"entry\" href=\"/detail/582ace7405c3fb3853030571\" target=\"_blank\">天皇重新掌权</a>。<a data-id=\"582acb9805c3fb5b4e030574\" data-type=\"entry\" href=\"/detail/582acb9805c3fb5b4e030574\" target=\"_blank\">明治天皇</a>在军事、司法、财政、教育等各方面进行<a data-id=\"582ac2f005c3fb0c4503057a\" data-type=\"entry\" href=\"/detail/582ac2f005c3fb0c4503057a\" target=\"_blank\">大规模改革</a>，使日本实现<a data-id=\"592422e555b54278ac00cc46\" data-type=\"entry\" href=\"/detail/592422e555b54278ac00cc46\" target=\"_blank\">工业化</a>及<a data-id=\"5924148b55b54278ac001b69\" data-type=\"entry\" href=\"/detail/5924148b55b54278ac001b69\" target=\"_blank\">现代化</a>。在19世纪末20世纪初，日本通过战争及外交手段成功实现了殖民扩张，成为当时世界的<a data-id=\"5910411355b542257a0001f0\" data-type=\"entry\" href=\"/detail/5910411355b542257a0001f0\" target=\"_blank\">帝国主义列强</a>之一。日本自1937年对中国发动<a data-id=\"57fef5240bd1be8273d7c187\" data-type=\"entry\" href=\"/detail/57fef5240bd1be8273d7c187\" target=\"_blank\">全面侵略</a>，后来成为<a data-id=\"57eb63f20bd1bef91d8b4567\" data-type=\"entry\" href=\"/detail/57eb63f20bd1bef91d8b4567\" target=\"_blank\">二战时期</a>的<a data-id=\"5910411255b542257a0001d3\" data-type=\"entry\" href=\"/detail/5910411255b542257a0001d3\" target=\"_blank\">轴心国</a>成员，珍珠港事件后，日本扩张战场至东南亚及太平洋，但最终于1945年<a data-id=\"59243bc655b54278ac01d472\" data-type=\"entry\" href=\"/detail/59243bc655b54278ac01d472\" target=\"_blank\">战败投降</a>。战败后，同盟国军事占领日本，并监督日本当局重新<a data-id=\"59241f0f55b54278ac009bab\" data-type=\"entry\" href=\"/detail/59241f0f55b54278ac009bab\" target=\"_blank\">制定宪法</a>，以及创建新的<a data-id=\"592415ee55b54278ac002b92\" data-type=\"entry\" href=\"/detail/592415ee55b54278ac002b92\" target=\"_blank\">政治架构</a>，规定<a data-id=\"59244e7055b54278ac02b4a5\" data-type=\"entry\" href=\"/detail/59244e7055b54278ac02b4a5\" target=\"_blank\">日本政府</a>采以<a data-id=\"59241d8155b54278ac0085c9\" data-type=\"entry\" href=\"/detail/59241d8155b54278ac0085c9\" target=\"_blank\">和平主义</a>、<a data-id=\"592448f155b54278ac026e16\" data-type=\"entry\" href=\"/detail/592448f155b54278ac026e16\" target=\"_blank\">国民主权</a>、与<a data-id=\"592413f655b54278ac001452\" data-type=\"entry\" href=\"/detail/592413f655b54278ac001452\" target=\"_blank\">基本人权</a>的尊重作为国家理念；天皇则成为<a data-id=\"592441f855b54278ac0213f1\" href=\"/detail/592441f855b54278ac0213f1\" target=\"_blank\">虚位元首</a>，主要从事<a data-id=\"5924262455b54278ac00f695\" data-type=\"entry\" href=\"/detail/5924262455b54278ac00f695\" target=\"_blank\">仪式</a>性的国事活动<sup class=\"sup-reference\" ref-id=\"ref-14\">[14]</sup>。日本亦需要依照<a data-id=\"592426d255b54278ac00fe4d\" data-type=\"entry\" href=\"/detail/592426d255b54278ac00fe4d\" target=\"_blank\">宪法第九条</a>放弃维持<a data-id=\"592413b955b54278ac0011d4\" data-type=\"entry\" href=\"/detail/592413b955b54278ac0011d4\" target=\"_blank\">武装</a>以及<a data-id=\"5924272a55b54278ac01029b\" data-type=\"entry\" href=\"/detail/5924272a55b54278ac01029b\" target=\"_blank\">宣战</a>权。法律上看似属于无军队国家，但是日本从未被<a data-id=\"59243f9f55b54278ac01ff61\" data-type=\"entry\" href=\"/detail/59243f9f55b54278ac01ff61\" target=\"_blank\">非军事化</a>，其拥有功能等同于其他<a data-id=\"592412b955b54278ac0002f0\" data-type=\"entry\" href=\"/detail/592412b955b54278ac0002f0\" target=\"_blank\">国家</a><a data-id=\"592413b955b54278ac0011d4\" data-type=\"entry\" href=\"/detail/592413b955b54278ac0011d4\" target=\"_blank\">军队</a>的<a data-id=\"5910558355b542257a01ea0a\" data-type=\"entry\" href=\"/detail/5910558355b542257a01ea0a\" target=\"_blank\">自卫队</a>。至1952年4月28日《<a data-id=\"5924165855b54278ac002fff\" data-type=\"entry\" href=\"/detail/5924165855b54278ac002fff\" target=\"_blank\">旧金山和约</a>》生效后，同盟国的军事占领结束，日本重新行使其主权。</p>\n\n<p>日本是<a data-id=\"59241f9655b54278ac00a263\" data-type=\"entry\" href=\"/detail/59241f9655b54278ac00a263\" target=\"_blank\">世界第三大经济体</a>，亦为<a data-id=\"592417b855b54278ac003f2a\" data-type=\"entry\" href=\"/detail/592417b855b54278ac003f2a\" target=\"_blank\">七国集团</a>成员，是世界少数<a data-id=\"5924166a55b54278ac0030cd\" data-type=\"entry\" href=\"/detail/5924166a55b54278ac0030cd\" target=\"_blank\">先进国家</a>之一。上世纪末，<a data-id=\"5924275c55b54278ac0104e5\" data-type=\"entry\" href=\"/detail/5924275c55b54278ac0104e5\" target=\"_blank\">日本经济</a>经历<a data-id=\"5924612455b54278ac03c672\" data-type=\"entry\" href=\"/detail/5924612455b54278ac03c672\" target=\"_blank\">显著增长</a>，得以重建战前的经济规模。现时日本的科研能力、工业基础和<a data-id=\"59241f7c55b54278ac00a1ad\" data-type=\"entry\" href=\"/detail/59241f7c55b54278ac00a1ad\" target=\"_blank\">制造业</a>技术均位居世界前茅，并是世界第四大<a data-id=\"59241b3755b54278ac006960\" data-type=\"entry\" href=\"/detail/59241b3755b54278ac006960\" target=\"_blank\">出口</a>国和<a data-id=\"59241b3755b54278ac006961\" data-type=\"entry\" href=\"/detail/59241b3755b54278ac006961\" target=\"_blank\">进口</a>国<sup class=\"sup-reference\" ref-id=\"ref-17\">[17]</sup>。2015年，日本的<a data-id=\"5924128855b54278ac0000c4\" data-type=\"entry\" href=\"/detail/5924128855b54278ac0000c4\" target=\"_blank\">人均国内生产总值</a>依国际汇率可兑换成接近四万美元，人均国民收入则在三万七千美元左右，人类发展指数亦一直维持在极高水平<sup class=\"sup-reference\" ref-id=\"ref-18\">[18]</sup>。</p>\n",
      "imageId": "599f971e1bc9226fdf5de14a",
      "imageUrl": "//pic.allhistory.com/T1PyKCBXJT1RCvBVdK.png",
      "itemWeight": 3.0883007,
      "itemTag": null,
      "disambiguation": "国家",
      "relations": {
        "direction": "->",
        "id": "5b6150762a99a6000155be5c",
        "relation": "奔赴",
        "relationDesc": "<div><a href=\"/detail/5910543755b542257a01cba6\" target=\"_blank\" style=\"font-weight: lighter;\">民国</a>十一年（1922年），在<a href=\"/detail/57c3d99c0bd1be8e01a0bda4\" target=\"_blank\">杭州</a>多位居士劝进及阅读《法轮宝忏》后，<a href=\"/detail/5924a75155b54278ac05f6bb\" target=\"_blank\">持松法师</a>与<a href=\"/detail/5910504e55b542257a0171bf\" target=\"_blank\">太虚大师</a>的弟子大勇，结伴东渡日本，到<a href=\"/detail/5924276255b54278ac01052d\" target=\"_blank\">高野山</a>真言宗道场，依金山穆韶阿阇黎修学密法，受古义真言宗中院一派的传授。</div>",
        "relationType": "LOCATION",
        "relationTypeGroup": null,
        "relationWeight": 47,
        "relationId": "5b6150762a99a6000155be5c",
        "time": {
          "startTime": "1922-00-00 00:00:00",
          "timeDesc": "",
          "endTime": "",
          "startAccuracy": null,
          "startNote": "",
          "endAccuracy": null,
          "endNote": ""
        },
        "position": [{
          "type": "Point",
          "coordinates": [139.239417880618, 36.5748440956015]
        }],
        "positionDesc": "日本",
        "properties": null,
        "relationCategoryGroup": "HUMAN_THING",
        "scoreMachine": null
      },
      "relatedPoint": 1,
      "typePaths": [{
        "name": "政治/政权行政区划/国家政权",
        "id": "2952"
      }],
      "categoryProp": null,
      "birth": null,
      "death": null,
      "relationList": null,
      "priorRelationTypes": null,
      "workType": null,
      "workIds": null,
      "auditing": false
    }, {
      "id": "57c3d97b0bd1befa7fa0bda8",
      "name": "南京市",
      "summary": "<p><strong>南京</strong>，简称&ldquo;宁&rdquo;，古称金陵、建康，是<a data-id=\"5910579855b542257a021c42\" href=\"/detail/5910579855b542257a021c42\" target=\"_blank\">江苏省</a>会、副省级市、特大城市、南京都市圈核心城市，国务院批复确定的中国东部地区重要的中心城市、全国重要的科研教育基地和综合交通枢纽。截至2018年，全市下辖11个区，总面积6587平方千米，建成区面积817平方千米。2019年，常住人口850.0万人，城镇人口707.2万人，城镇化率83.2%。</p>\n\n<p>南京地处中国东部、<a data-id=\"58de0e28977fd54119fa20a9\" href=\"/detail/58de0e28977fd54119fa20a9\" target=\"_blank\">长江</a>下游、濒江近海，是中国东部战区司令部驻地，地理坐标为北纬31&deg;14&Prime;至32&deg;37&Prime;，东经118&deg;22&Prime;至119&deg;14&Prime;，是国务院规划定位的长三角辐射带动中西部地区发展的重要门户城市，也是东部沿海经济带与长江经济带战略交汇的重要节点城市。</p>\n\n<p>南京属宁镇扬丘陵地区，以低山缓岗为主，属北亚热带湿润气候，水域面积达11%以上，是首批国家历史文化名城，中华文明的重要发祥地，长期是中国南方的政治、经济、文化中心。南京早在100-120万年前就有古人类活动，35-60万年前已有南京猿人在汤山生活，有着7000多年文明史、近2600年建城史和近500年的建都史。</p>\n\n<p>南京是国家重要的科教中心，自古以来就是一座崇文重教的城市，有&ldquo;天下文枢&rdquo;、&ldquo;东南第一学&rdquo;之称，<a data-id=\"57c93da50bd1bee11a8b456f\" href=\"/detail/57c93da50bd1bee11a8b456f\" target=\"_blank\">明</a><a data-id=\"582ac88705c3fb234e030571\" href=\"/detail/582ac88705c3fb234e030571\" target=\"_blank\">清</a>中国一半以上的状元均出自南京江南贡院 。截至2018年，南京各类高等院校66所，其中111计划高校10所、学科25个；211高校8所、双一流高校12所、两院院士81人。</p>\n",
      "imageId": "599f972c1bc9226fdf5dece3",
      "imageUrl": "//pic.allhistory.com/T1q7ZvB4bT1RCvBVdK.png",
      "itemWeight": 2.699737,
      "itemTag": null,
      "disambiguation": "城市",
      "relations": {
        "direction": "->",
        "id": "5b6155972a99a6000155c02e",
        "relation": "讲法于",
        "relationDesc": "<div><a href=\"/detail/5910543755b542257a01cba6\" target=\"_blank\" style=\"font-weight: lighter;\">民国</a>十九年（1930年）下半年，<a href=\"/detail/5924a75155b54278ac05f6bb\" target=\"_blank\">持松法师</a>于<a href=\"/detail/57c3d97b0bd1befa7fa0bda8\" target=\"_blank\">南京</a>功德林讲《大日经·住心品》。</div>",
        "relationType": "LOCATION",
        "relationTypeGroup": null,
        "relationWeight": 79,
        "relationId": "5b6155972a99a6000155c02e",
        "time": {
          "startTime": "1930-00-00 00:00:00",
          "timeDesc": "",
          "endTime": "",
          "startAccuracy": null,
          "startNote": "",
          "endAccuracy": null,
          "endNote": ""
        },
        "position": [{
          "type": "Point",
          "coordinates": [118.76666666667, 32.05]
        }],
        "positionDesc": "南京市",
        "properties": null,
        "relationCategoryGroup": "HUMAN_THING",
        "scoreMachine": null
      },
      "relatedPoint": 1,
      "typePaths": [{
        "name": "政治/政权行政区划/城市村镇",
        "id": "2961"
      }],
      "categoryProp": null,
      "birth": null,
      "death": null,
      "relationList": null,
      "priorRelationTypes": null,
      "workType": null,
      "workIds": null,
      "auditing": false
    }, {
      "id": "5910543855b542257a01cbb0",
      "name": "尼泊尔",
      "summary": "<p><b>尼泊尔</b>（<a data-id=\"5910638555b542257a033cb9\" data-type=\"entry\" href=\"/detail/5910638555b542257a033cb9\" target=\"_blank\">尼泊尔语</a>：<span>नेपाल</span><sup class=\"sup-reference\" ref-id=\"ref-4\">[4]</sup>）全称为<b>尼泊尔联邦<span>民主</span>共和国</b>（<span>संघीय लोकतान्त्रिक गणतन्त्रात्मक नेपाल</span>），是<a data-id=\"5924128255b54278ac000087\" data-type=\"entry\" href=\"/detail/5924128255b54278ac000087\" target=\"_blank\">南亚</a><a data-id=\"58f8839b55b54258e70000b7\" data-type=\"entry\" href=\"/detail/58f8839b55b54258e70000b7\" target=\"_blank\">喜马拉雅山脉</a>地区的一个<a data-id=\"5924145155b54278ac00189e\" data-type=\"entry\" href=\"/detail/5924145155b54278ac00189e\" target=\"_blank\">内陆国家</a>，北与<a data-id=\"57eb64f60bd1beac1f8b4567\" data-type=\"entry\" href=\"/detail/57eb64f60bd1beac1f8b4567\" target=\"_blank\">中国</a>相接，其余三面与<a data-id=\"58a67359977fd5765b9fe113\" data-type=\"entry\" href=\"/detail/58a67359977fd5765b9fe113\" target=\"_blank\">印度</a>为邻。尼泊尔的土地面积为14万7181平方公里，为世界上第93大<sup class=\"sup-reference\" ref-id=\"ref-5\">[5]</sup>，2640万人口则排名世界上第41位。由于地处高海拔地区，世界上最高的十座山峰中有八座位于尼泊尔境内，包括最高峰<a data-id=\"5910565f55b542257a01feb3\" data-type=\"entry\" href=\"/detail/5910565f55b542257a01feb3\" target=\"_blank\">珠穆朗玛峰</a>。</p>\n\n<p>尼泊尔拥有古老的文化遗产，<a data-id=\"57c39acd0bd1be226ea0bda3\" data-type=\"entry\" href=\"/detail/57c39acd0bd1be226ea0bda3\" target=\"_blank\">佛教</a>创始人<a data-id=\"5924139855b54278ac00106e\" data-type=\"entry\" href=\"/detail/5924139855b54278ac00106e\" target=\"_blank\">佛陀</a><a data-id=\"57c4ebb60bd1be5607a0bdb0\" data-type=\"entry\" href=\"/detail/57c4ebb60bd1be5607a0bdb0\" target=\"_blank\">释迦牟尼</a>即出生在尼泊尔。国家主体宗教信仰为<a data-id=\"5885b9b9bf69284e60f64720\" data-type=\"entry\" href=\"/detail/5885b9b9bf69284e60f64720\" target=\"_blank\">印度教</a>，另有少数群体信仰藏传佛教、<span>伊斯兰</span>教等。尼泊尔还以骁勇善战的<a data-id=\"5910572f55b542257a0211c8\" data-type=\"entry\" href=\"/detail/5910572f55b542257a0211c8\" target=\"_blank\">廓尔喀人</a>士兵闻名于世。</p>\n\n<p>18世纪中期建立了<a data-id=\"59104cb055b542257a011b1d\" data-type=\"entry\" href=\"/detail/59104cb055b542257a011b1d\" target=\"_blank\">尼泊尔王国</a>，并曾<a data-id=\"59104a0d55b542257a00df60\" data-type=\"entry\" href=\"/detail/59104a0d55b542257a00df60\" target=\"_blank\">试图入侵<span><span>西藏</span></span></a>，后成为清朝<a data-id=\"58de32f3977fd54119fa20c3\" data-type=\"entry\" href=\"/detail/58de32f3977fd54119fa20c3\" target=\"_blank\">藩属国</a>。在19世纪初<a data-id=\"5910652755b542257a0363fc\" data-type=\"entry\" href=\"/detail/5910652755b542257a0363fc\" target=\"_blank\">英尼战争</a>后尼泊尔割地予<a data-id=\"59104cb655b542257a011b81\" data-type=\"entry\" href=\"/detail/59104cb655b542257a011b81\" target=\"_blank\">英属印度</a>并与其结盟。尼泊尔原为<a data-id=\"5885b9b9bf69284e60f64720\" data-type=\"entry\" href=\"/detail/5885b9b9bf69284e60f64720\" target=\"_blank\">印度教</a><a data-id=\"57c399c00bd1beef76a0bda4\" data-type=\"entry\" href=\"/detail/57c399c00bd1beef76a0bda4\" target=\"_blank\">君主制</a>国家。2006年，<a data-id=\"5924142555b54278ac0016a5\" data-type=\"entry\" href=\"/detail/5924142555b54278ac0016a5\" target=\"_blank\">国会</a>冻结了<a data-id=\"59249a3a55b54278ac055146\" data-type=\"entry\" href=\"/detail/59249a3a55b54278ac055146\" target=\"_blank\">国王</a><a data-id=\"591ae63955b5427dfa0215e3\" data-type=\"entry\" href=\"/detail/591ae63955b5427dfa0215e3\" target=\"_blank\">贾南德拉</a>的权力，2008年，尼泊尔制宪会议正式通过宪法修正案，废除<a data-id=\"57c399c00bd1beef76a0bda4\" data-type=\"entry\" href=\"/detail/57c399c00bd1beef76a0bda4\" target=\"_blank\">君主制</a>改国号为尼泊尔联邦<span>民主</span>共和国。</p>\n",
      "imageId": "599f98721bc9226fdf5f72c6",
      "imageUrl": "//pic.allhistory.com/T1j2JvBXVT1RCvBVdK.jpg",
      "itemWeight": 3.013236,
      "itemTag": null,
      "disambiguation": "",
      "relations": {
        "direction": "->",
        "id": "5b6156fe2a99a6000155c08a",
        "relation": "前往",
        "relationDesc": "<div>1956年11月，<a href=\"/detail/5924a75155b54278ac05f6bb\" target=\"_blank\">持松法师</a>随中国佛教代表团，参加在<a href=\"/detail/5910543855b542257a01cbb0\" target=\"_blank\">尼泊尔</a>举行的第四届世界佛教代表大会。</div>",
        "relationType": "LOCATION",
        "relationTypeGroup": null,
        "relationWeight": 37,
        "relationId": "5b6156fe2a99a6000155c08a",
        "time": {
          "startTime": "1956-11-00 00:00:00",
          "timeDesc": "",
          "endTime": "",
          "startAccuracy": null,
          "startNote": "",
          "endAccuracy": null,
          "endNote": ""
        },
        "position": [{
          "type": "Point",
          "coordinates": [84.0917514882943, 28.1082106964014]
        }],
        "positionDesc": "尼泊尔",
        "properties": null,
        "relationCategoryGroup": "HUMAN_THING",
        "scoreMachine": null
      },
      "relatedPoint": 1,
      "typePaths": [{
        "name": "政治/政权行政区划/国家政权",
        "id": "2952"
      }],
      "categoryProp": null,
      "birth": null,
      "death": null,
      "relationList": null,
      "priorRelationTypes": null,
      "workType": null,
      "workIds": null,
      "auditing": false
    }, {
      "id": "5910543955b542257a01cbb4",
      "name": "印度尼西亚",
      "summary": "<p><b>印度尼西亚共和国</b>（<a data-id=\"5910638455b542257a033c96\" data-type=\"entry\" href=\"/detail/5910638455b542257a033c96\" target=\"_blank\">印尼语</a>：<span><b>Republik Indonesia</b></span>，<a data-id=\"59105dd255b542257a02b0a7\" data-type=\"entry\" href=\"/detail/59105dd255b542257a02b0a7\" target=\"_blank\">IPA</a>读音：<span class=\"IPA\" style=\"font-family: 'Charis SIL', 'Doulos SIL', 'Linux Libertine', 'Segoe UI', 'Lucida Sans Unicode', 'Code2000', 'Gentium', 'Gentium Alternative', 'TITUS Cyberbit Basic', 'Arial Unicode MS', 'IPAPANNEW', 'Chrysanthi Unicode', 'GentiumAlt', 'Bitstream Vera', 'Bitstream Cyberbit', 'Hiragino Kaku Gothic Pro', 'Lucida Grande', sans-serif; text-d&lt;span &gt;eco&lt;/span&gt;ration:none!important\">[rɛpʊblɪk ɪndɔnɛsɪa]</span>），简称<b>印度尼西亚</b>或<b>印尼</b>，为<a data-id=\"58f8853b55b54258e700299f\" data-type=\"entry\" href=\"/detail/58f8853b55b54258e700299f\" target=\"_blank\">东南亚</a><a data-id=\"592412b955b54278ac0002f0\" data-type=\"entry\" href=\"/detail/592412b955b54278ac0002f0\" target=\"_blank\">国家</a>；约由17,508个<a data-id=\"592412e855b54278ac0004eb\" data-type=\"entry\" href=\"/detail/592412e855b54278ac0004eb\" target=\"_blank\">岛屿</a>组成<sup class=\"sup-reference\" ref-id=\"ref-8\">[8]</sup>，是世界上最大的<a data-id=\"5924226055b54278ac00c4c9\" data-type=\"entry\" href=\"/detail/5924226055b54278ac00c4c9\" target=\"_blank\">群岛</a>国家，疆域横跨<a data-id=\"5910413c55b542257a000577\" data-type=\"entry\" href=\"/detail/5910413c55b542257a000577\" target=\"_blank\">亚洲</a>及<a data-id=\"5910413d55b542257a000578\" data-type=\"entry\" href=\"/detail/5910413d55b542257a000578\" target=\"_blank\">大洋洲</a>，别称&ldquo;万岛之国<sup class=\"sup-note\" note-id=\"note-1\">[注]</sup>&rdquo;<sup class=\"sup-reference\" ref-id=\"ref-10\">[10]</sup><sup class=\"sup-reference\" ref-id=\"ref-11\">[11]</sup><sup class=\"sup-reference\" ref-id=\"ref-12\">[12]</sup><sup class=\"sup-reference\" ref-id=\"ref-13\">[13]</sup><sup class=\"sup-reference\" ref-id=\"ref-14\">[14]</sup><sup class=\"sup-reference\" ref-id=\"ref-15\">[15]</sup>。印度尼西亚人口超过2.58亿，为世界上人口<a data-id=\"5924128055b54278ac000077\" data-type=\"entry\" href=\"/detail/5924128055b54278ac000077\" target=\"_blank\">第四多</a>的国家。<a data-id=\"59243c6755b54278ac01dcdf\" data-type=\"entry\" href=\"/detail/59243c6755b54278ac01dcdf\" target=\"_blank\">国体</a>属<a data-id=\"57c7e19c0bd1bedd168b4567\" data-type=\"entry\" href=\"/detail/57c7e19c0bd1bedd168b4567\" target=\"_blank\">共和国</a>，国会代表及总统皆由选举产生。印度尼西亚首都为<a data-id=\"5910434b55b542257a0033d6\" data-type=\"entry\" href=\"/detail/5910434b55b542257a0033d6\" target=\"_blank\">雅加达</a>。印度尼西亚国界与<a data-id=\"5910543c55b542257a01cbea\" data-type=\"entry\" href=\"/detail/5910543c55b542257a01cbea\" target=\"_blank\">巴布亚新几内亚</a>、<a data-id=\"5910543755b542257a01cbaa\" data-type=\"entry\" href=\"/detail/5910543755b542257a01cbaa\" target=\"_blank\">东帝汶</a>和<a data-id=\"5910543955b542257a01cbb6\" data-type=\"entry\" href=\"/detail/5910543955b542257a01cbb6\" target=\"_blank\">马来西亚</a>相接，另有<a data-id=\"5910544255b542257a01cc50\" data-type=\"entry\" href=\"/detail/5910544255b542257a01cc50\" target=\"_blank\">新加坡</a>、<a data-id=\"5910543755b542257a01cba9\" data-type=\"entry\" href=\"/detail/5910543755b542257a01cba9\" target=\"_blank\">菲律宾</a>及<a data-id=\"58f8855c55b54258e7002cc4\" data-type=\"entry\" href=\"/detail/58f8855c55b54258e7002cc4\" target=\"_blank\">澳大利亚</a>等其他邻国。印度尼西亚为<a data-id=\"58f8846655b54258e700148b\" data-type=\"entry\" href=\"/detail/58f8846655b54258e700148b\" target=\"_blank\">东南亚国家联盟</a>创立国之一，且为<a data-id=\"58f8859655b54258e7003239\" data-type=\"entry\" href=\"/detail/58f8859655b54258e7003239\" target=\"_blank\">20国集团</a>成员国。在2012年﹐依国际汇率计算，印度尼西亚为<a data-id=\"59241f9655b54278ac00a263\" data-type=\"entry\" href=\"/detail/59241f9655b54278ac00a263\" target=\"_blank\">世界第16大经济体</a><sup class=\"sup-reference\" ref-id=\"ref-16\">[16]</sup>，以<a data-id=\"5924133f55b54278ac00097e\" data-type=\"entry\" href=\"/detail/5924133f55b54278ac00097e\" target=\"_blank\">购买力平价</a>计算则为<a data-id=\"59241d9855b54278ac008701\" data-type=\"entry\" href=\"/detail/59241d9855b54278ac008701\" target=\"_blank\">世界15大经济体</a><sup class=\"sup-reference\" ref-id=\"ref-17\">[17]</sup>。</p>\n\n<p>印度尼西亚群岛自7世纪起即为重要贸易地区，古代王国<a data-id=\"59104cb055b542257a011b25\" data-type=\"entry\" href=\"/detail/59104cb055b542257a011b25\" target=\"_blank\">三佛齐</a>及之后的<a data-id=\"59104cb055b542257a011b26\" data-type=\"entry\" href=\"/detail/59104cb055b542257a011b26\" target=\"_blank\">满者伯夷</a>曾与中国和印度进行贸易。印度尼西亚当地统治者逐步吸收外国文化、宗教和政治型态，曾出现兴盛的<a data-id=\"57c39acd0bd1be226ea0bda3\" data-type=\"entry\" href=\"/detail/57c39acd0bd1be226ea0bda3\" target=\"_blank\">佛教</a>和<a data-id=\"5885b9b9bf69284e60f64720\" data-type=\"entry\" href=\"/detail/5885b9b9bf69284e60f64720\" target=\"_blank\">印度教</a>王国。外国势力因天然资源而进入印度尼西亚，<a data-id=\"58f89b9b977fd57721c3d4ad\" data-type=\"entry\" href=\"/detail/58f89b9b977fd57721c3d4ad\" target=\"_blank\"><span>穆斯林</span></a>商人带入<a data-id=\"57bff8920bd1be7e478b4568\" data-type=\"entry\" href=\"/detail/57bff8920bd1be7e478b4568\" target=\"_blank\"><span>伊斯兰</span>教</a>，<a data-id=\"57ea3b840bd1be6c4c4dcb3e\" data-type=\"entry\" href=\"/detail/57ea3b840bd1be6c4c4dcb3e\" target=\"_blank\">欧洲</a>势力则带来了<a data-id=\"57bff8a60bd1be5b488b456a\" data-type=\"entry\" href=\"/detail/57bff8a60bd1be5b488b456a\" target=\"_blank\">基督教</a>，并于<a data-id=\"5924344e55b54278ac01a254\" data-type=\"entry\" href=\"/detail/5924344e55b54278ac01a254\" target=\"_blank\">地理大发现</a>后垄断香料群岛<a data-id=\"5910563455b542257a01faba\" data-type=\"entry\" href=\"/detail/5910563455b542257a01faba\" target=\"_blank\">马鲁古群岛</a>的贸易。在350年的<a data-id=\"59104cb455b542257a011b62\" data-type=\"entry\" href=\"/detail/59104cb455b542257a011b62\" target=\"_blank\">荷兰殖民统治时期</a>后，印度尼西亚至<a data-id=\"57eb63f20bd1bef91d8b4567\" data-type=\"entry\" href=\"/detail/57eb63f20bd1bef91d8b4567\" target=\"_blank\">第二次世界大战</a>后始告独立，但独立后仍面临天灾、贪污、分离主义、<span>民主</span>化进程、经济上剧变等挑战。</p>\n\n<p>由于岛屿遍布，印度尼西亚有数百个不同民族及语言，最大的族群为<a data-id=\"59104c2755b542257a010e05\" data-type=\"entry\" href=\"/detail/59104c2755b542257a010e05\" target=\"_blank\">爪哇族</a>，并在政治上居主导地位<sup class=\"sup-reference\" ref-id=\"ref-18\">[18]</sup>。国家语言、种族多样性、<span>穆斯林</span>占多数人口、殖民历史及反抗殖民为印度尼西亚人的共同身份。印度尼西亚国家格言&ldquo;Bhinneka Tunggal Ika<sup class=\"sup-note\" note-id=\"note-2\">[注]</sup>&rdquo;（存异求同）阐明了多样性及国家的型态。虽然人口众多且稠密，但大部分都在特定的大岛上，所以印度尼西亚仍保有大量的原野，且<a data-id=\"59241c5255b54278ac0076d0\" data-type=\"entry\" href=\"/detail/59241c5255b54278ac0076d0\" target=\"_blank\">生物多样性</a>居世界第二位。国家的天然资源丰富，但贫穷仍相当普遍，因而在世界各地有不少的印尼籍移工，但也有针对该地天然资源保育或收获而来的西方人，国际交流程度不低。<sup class=\"sup-reference\" ref-id=\"ref-19\">[19]</sup><sup class=\"sup-reference\" ref-id=\"ref-20\">[20]</sup><sup class=\"sup-reference\" ref-id=\"ref-21\">[21]</sup></p>\n",
      "imageId": "599f98721bc9226fdf5f72ce",
      "imageUrl": "//pic.allhistory.com/T1oaCCBTAg1RCvBVdK.png",
      "itemWeight": 3.059812,
      "itemTag": null,
      "disambiguation": "",
      "relations": {
        "direction": "->",
        "id": "5b6157bd2a99a6000155c0b3",
        "relation": "访问",
        "relationDesc": "<div>1965年，<a href=\"/detail/5924a75155b54278ac05f6bb\" target=\"_blank\">持松法师</a>随中国佛教代表团访问<a href=\"/detail/5910543955b542257a01cbb4\" target=\"_blank\">印尼</a>。</div>",
        "relationType": "LOCATION",
        "relationTypeGroup": null,
        "relationWeight": 53,
        "relationId": "5b6157bd2a99a6000155c0b3",
        "time": {
          "startTime": "1965-00-00 00:00:00",
          "timeDesc": "",
          "endTime": "",
          "startAccuracy": null,
          "startNote": "",
          "endAccuracy": null,
          "endNote": ""
        },
        "position": [{
          "type": "Point",
          "coordinates": [114.563203184053, -4.79933559933349]
        }],
        "positionDesc": "印度尼西亚",
        "properties": null,
        "relationCategoryGroup": "HUMAN_THING",
        "scoreMachine": null
      },
      "relatedPoint": 1,
      "typePaths": [{
        "name": "政治/政权行政区划/国家政权",
        "id": "2952"
      }],
      "categoryProp": null,
      "birth": null,
      "death": null,
      "relationList": null,
      "priorRelationTypes": null,
      "workType": null,
      "workIds": null,
      "auditing": false
    }, {
      "id": "591acb0155b5427dfa018d3f",
      "name": "归元寺",
      "summary": "<p>归元寺，位于<a href=\"http://www.evatlas.com/detail/592419c555b54278ac005719\">汉阳区</a>翠微路和归元寺路交界，是<a href=\"http://www.evatlas.com/detail/58de0ec2977fd5867ffa20d0\">湖北省</a><a href=\"http://www.evatlas.com/detail/591059b855b542257a025025\">武汉市</a>的一座著名<a href=\"http://www.evatlas.com/detail/57c39acd0bd1be226ea0bda3\">佛教</a><a href=\"http://www.evatlas.com/detail/59241c1455b54278ac0073e3\">曹洞宗</a>寺院，武汉的佛教四大丛林(还包括<a href=\"http://www.evatlas.com/detail/591acb0f55b5427dfa018e65\">宝通寺</a>、<a href=\"http://www.evatlas.com/detail/591acc7d55b5427dfa01af87\">莲溪寺</a>、正觉寺）之一。<a href=\"http://www.evatlas.com/detail/58de0ec2977fd5867ffa20d0\">湖北省</a>佛教协会和<a href=\"http://www.evatlas.com/detail/591059b855b542257a025025\">武汉市</a>佛教协会的所在地，<a href=\"http://www.evatlas.com/detail/58de0ec2977fd5867ffa20d0\">湖北省</a><a href=\"http://www.evatlas.com/detail/59241b2b55b54278ac0068de\">文物保护单位</a>。国务院首批公布的开展宗教活动的重点寺庙。寺名取佛经&ldquo;归元性不二，方便有多门&rdquo;之语意。藏经阁内供奉有<a href=\"http://www.evatlas.com/detail/57c4ebb60bd1be5607a0bdb0\">释迦牟尼</a><a href=\"http://www.evatlas.com/detail/5924302055b54278ac016bda\">佛像</a>。</p>\n",
      "imageId": "599f9aab1bc9226fdf6189a4",
      "imageUrl": "//pic.allhistory.com/T1gkdvByYT1RCvBVdK.JPG",
      "itemWeight": 0.698081,
      "itemTag": null,
      "disambiguation": "",
      "relations": {
        "direction": "->",
        "id": "5b614e982a99a6000155bdd8",
        "relation": "受具足戒于",
        "relationDesc": "<div><a href=\"/detail/5910543755b542257a01cba6\" target=\"_blank\" style=\"font-weight: lighter;\">民国</a>元年（1912年）十二月八号，<a href=\"/detail/5924a75155b54278ac05f6bb\" target=\"_blank\">持松法师</a>到汉阳<a href=\"/detail/591acb0155b5427dfa018d3f\" target=\"_blank\">归元寺</a>受具足戒。</div>",
        "relationType": "LOCATION",
        "relationTypeGroup": null,
        "relationWeight": 38,
        "relationId": "5b614e982a99a6000155bdd8",
        "time": {
          "startTime": "1912-00-00 00:00:00",
          "timeDesc": "",
          "endTime": "",
          "startAccuracy": null,
          "startNote": "",
          "endAccuracy": null,
          "endNote": ""
        },
        "position": [{
          "type": "Point",
          "coordinates": [114.26514, 30.54979]
        }],
        "positionDesc": "汉阳区",
        "properties": null,
        "relationCategoryGroup": null,
        "scoreMachine": null
      },
      "relatedPoint": 1,
      "typePaths": [{
        "name": "文化/古迹",
        "id": "1040"
      }],
      "categoryProp": null,
      "birth": null,
      "death": null,
      "relationList": null,
      "priorRelationTypes": null,
      "workType": null,
      "workIds": null,
      "auditing": false
    }, {
      "id": "58b53a37977fd5c8623ce7d7",
      "name": "汉阳",
      "summary": "<p><b>汉阳</b>，是指武汉人习惯按“武汉三镇”的说法将<a data-id=\"58de0e28977fd54119fa20a9\" data-type=\"entry\" href=\"/detail/58de0e28977fd54119fa20a9\" target=\"_blank\">长江</a>以北、汉江以南市区部分称为<b>汉阳</b>的地方，包括<b><a data-id=\"592419c555b54278ac005719\" data-type=\"entry\" href=\"/detail/592419c555b54278ac005719\" target=\"_blank\">汉阳区</a></b>、<b><a data-id=\"5910663e55b542257a037d52\" data-type=\"entry\" href=\"/detail/5910663e55b542257a037d52\" target=\"_blank\">武汉经济技术开发区</a></b>两个行政区划，有时还包括<b><a data-id=\"59241d7555b54278ac00852e\" data-type=\"entry\" href=\"/detail/59241d7555b54278ac00852e\" target=\"_blank\">蔡甸区</a></b>（原称<b><a data-id=\"5924349855b54278ac01a571\" data-type=\"entry\" href=\"/detail/5924349855b54278ac01a571\" target=\"_blank\">汉阳县</a></b>，<a data-id=\"591059b855b542257a025025\" data-type=\"entry\" href=\"/detail/591059b855b542257a025025\" target=\"_blank\">武汉市</a>的郊区）。</p>\n",
      "imageId": "",
      "imageUrl": "",
      "itemWeight": 0.3842303,
      "itemTag": null,
      "disambiguation": "武汉三镇",
      "relations": {
        "direction": "->",
        "id": "5b6153e22a99a6000155bfee",
        "relation": "讲法于",
        "relationDesc": "<div><a href=\"/detail/5910543755b542257a01cba6\" target=\"_blank\" style=\"font-weight: lighter;\">民国</a>十九年（1930年）春，<a href=\"/detail/5924a75155b54278ac05f6bb\" target=\"_blank\">持松法师</a>在汉阳，于归元寺讲《楞严经》。</div>",
        "relationType": "LOCATION",
        "relationTypeGroup": null,
        "relationWeight": 88,
        "relationId": "5b6153e22a99a6000155bfee",
        "time": {
          "startTime": "1930-00-00 00:00:00",
          "timeDesc": "",
          "endTime": "",
          "startAccuracy": null,
          "startNote": "",
          "endAccuracy": null,
          "endNote": ""
        },
        "position": [{
          "type": "Point",
          "coordinates": [114.26514, 30.54979]
        }],
        "positionDesc": "汉阳区",
        "properties": null,
        "relationCategoryGroup": "HUMAN_THING",
        "scoreMachine": null
      },
      "relatedPoint": 1,
      "typePaths": [{
        "name": "政治/政权行政区划/行政区划",
        "id": "2954"
      }],
      "categoryProp": null,
      "birth": null,
      "death": null,
      "relationList": null,
      "priorRelationTypes": null,
      "workType": null,
      "workIds": null,
      "auditing": false
    }, {
      "id": "59241d8855b54278ac00862d",
      "name": "沙洋县",
      "summary": "<p><b>沙洋县</b>位于<a data-id=\"57eb64f60bd1beac1f8b4567\" data-type=\"entry\" href=\"/detail/57eb64f60bd1beac1f8b4567\" target=\"_blank\">中国</a><a data-id=\"58de0ec2977fd5867ffa20d0\" data-type=\"entry\" href=\"/detail/58de0ec2977fd5867ffa20d0\" target=\"_blank\">湖北省</a>中部，是<a data-id=\"591059c055b542257a02509d\" data-type=\"entry\" href=\"/detail/591059c055b542257a02509d\" target=\"_blank\">荆门市</a>所辖的一个<a data-id=\"59244b2b55b54278ac028c82\" data-type=\"entry\" href=\"/detail/59244b2b55b54278ac028c82\" target=\"_blank\">县</a>。面积为2044平方公里，2006年人口为59万人。</p>\n",
      "imageId": "",
      "imageUrl": "",
      "itemWeight": 1.26824,
      "itemTag": null,
      "disambiguation": "",
      "relations": {
        "direction": "->",
        "id": "5b614dc22a99a6000155bda6",
        "relation": "出生于",
        "relationDesc": "<div><div><a href=\"/detail/591adc0c55b5427dfa02083e\" target=\"_blank\" style=\"font-weight: lighter;\">光绪</a>二十年七月十三号（1894年8月13号），<a href=\"/detail/5924a75155b54278ac05f6bb\" target=\"_blank\">持松法师</a>生于荆门直隶州沙洋张家潭（今<a href=\"/detail/58de0ec2977fd5867ffa20d0\" target=\"_blank\">湖北省</a><a href=\"/detail/59241d8855b54278ac00862d\" target=\"_blank\">沙洋县</a>城南青泥村）。</div></div>",
        "relationType": "LOCATION",
        "relationTypeGroup": null,
        "relationWeight": 10,
        "relationId": "5b614dc22a99a6000155bda6",
        "time": {
          "startTime": "1894-00-00 00:00:00",
          "timeDesc": "清光绪帝光绪二十年七月十三号",
          "endTime": "",
          "startAccuracy": null,
          "startNote": "",
          "endAccuracy": null,
          "endNote": ""
        },
        "position": [{
          "type": "Point",
          "coordinates": [112.396704984354, 30.6653072961393]
        }],
        "positionDesc": "张家潭（今湖北省沙洋县）",
        "properties": null,
        "relationCategoryGroup": "HUMAN_THING",
        "scoreMachine": null
      },
      "relatedPoint": 1,
      "typePaths": [{
        "name": "政治/政权行政区划/行政区划",
        "id": "2954"
      }],
      "categoryProp": null,
      "birth": null,
      "death": null,
      "relationList": null,
      "priorRelationTypes": null,
      "workType": null,
      "workIds": null,
      "auditing": false
    }, {
      "id": "591acc7d55b5427dfa01af87",
      "name": "莲溪寺",
      "summary": "<p><b>莲溪寺</b>位于武汉市武昌区涂家岭四村51号，古籍中记载此地原名&ldquo;蟠龙山&rdquo;。莲溪寺是武汉市&ldquo;四大丛林&rdquo;，所谓丛林，就是僧侣聚集之处，民国十七年（1928年）体空禅师在此开办了当时全国佛教的最高学府华严大学。尤为难得的是，自1994年莲溪寺的&ldquo;女众部&rdquo;搬迁至此后，莲溪寺成为武汉市内仅有的两处专供女性修行的寺院之一（另一所为<a data-id=\"592442f955b54278ac0220a9\" data-type=\"entry\" href=\"/detail/592442f955b54278ac0220a9\" target=\"_blank\">蛇山</a>脚下的龙华禅寺）。</p>\n\n<p>寺院始建于元末明初，于明末毁于战乱，但于<a data-id=\"591adc0c55b5427dfa02083b\" data-type=\"entry\" href=\"/detail/591adc0c55b5427dfa02083b\" target=\"_blank\">康熙</a>年间由法融禅师主持重修，又于咸丰六年（1856年）为<a data-id=\"57c3d6100bd1bef87fa0bda3\" data-type=\"entry\" href=\"/detail/57c3d6100bd1bef87fa0bda3\" target=\"_blank\">太平军</a>所毁。现存建筑为光绪十五年（1898年）重修，寺院于2013年开始大兴土木至今尚未完工。</p>\n\n<p>寺院现存建筑分四进：入山门为禅堂、中为弥勒殿、复为大雄宝殿、更进为藏经阁。藏经阁内藏有<a data-id=\"59243a5955b54278ac01cf13\" data-type=\"entry\" href=\"/detail/59243a5955b54278ac01cf13\" target=\"_blank\">乾隆大藏经</a>一部，更藏有一尊北魏时期墨玉观音像为镇寺之至宝；寺内亦有上至元末下至民国石碑数座，均为不可多得的历史见证。</p>\n",
      "imageId": "",
      "imageUrl": "",
      "itemWeight": 0.34501442,
      "itemTag": null,
      "disambiguation": "",
      "relations": {
        "direction": "->",
        "id": "5b6155542a99a6000155c022",
        "relation": "讲法于",
        "relationDesc": "<div><a href=\"/detail/5910543755b542257a01cba6\" target=\"_blank\" style=\"font-weight: lighter;\">民国</a>十九年（1930年）下半年，<a href=\"/detail/5924a75155b54278ac05f6bb\" target=\"_blank\">持松法师</a>于武昌<a href=\"/detail/591acc7d55b5427dfa01af87\" target=\"_blank\">莲溪寺</a>讲《护国仁王经》。</div>",
        "relationType": "LOCATION",
        "relationTypeGroup": null,
        "relationWeight": 54,
        "relationId": "5b6155542a99a6000155c022",
        "time": {
          "startTime": "1930-00-00 00:00:00",
          "timeDesc": "",
          "endTime": "",
          "startAccuracy": null,
          "startNote": "",
          "endAccuracy": null,
          "endNote": ""
        },
        "position": [{
          "type": "Point",
          "coordinates": [114.31054, 30.55628]
        }],
        "positionDesc": "武昌区",
        "properties": null,
        "relationCategoryGroup": null,
        "scoreMachine": null
      },
      "relatedPoint": 1,
      "typePaths": [{
        "name": "文化/古迹",
        "id": "1040"
      }],
      "categoryProp": null,
      "birth": null,
      "death": null,
      "relationList": null,
      "priorRelationTypes": null,
      "workType": null,
      "workIds": null,
      "auditing": false
    }, {
      "id": "591acb0f55b5427dfa018e65",
      "name": "宝通寺",
      "summary": "<p><b>宝通寺</b>，又名<b>宝通禅寺</b>，位于<a data-id=\"591059b855b542257a025025\" data-type=\"entry\" href=\"/detail/591059b855b542257a025025\" target=\"_blank\">武汉市</a><a data-id=\"591042ce55b542257a002965\" data-type=\"entry\" href=\"/detail/591042ce55b542257a002965\" target=\"_blank\">武昌区</a><a data-id=\"5910431055b542257a002ed2\" data-type=\"entry\" href=\"/detail/5910431055b542257a002ed2\" target=\"_blank\">洪山</a>南麓，为武汉四大佛教丛林之一。1959年被列为武汉市文物保护单位，1992年被列为<a data-id=\"5924410255b54278ac02084f\" data-type=\"entry\" href=\"/detail/5924410255b54278ac02084f\" target=\"_blank\">湖北省文物保护单位</a>。</p>\n<p>宝通禅寺始建于南朝<a data-id=\"59104b9a55b542257a01013b\" data-type=\"entry\" href=\"/detail/59104b9a55b542257a01013b\" target=\"_blank\">刘宋</a>年间，初名<b>东山寺</b>，后<a data-id=\"57c404040bd1be7507a0bda8\" data-type=\"entry\" href=\"/detail/57c404040bd1be7507a0bda8\" target=\"_blank\">唐</a>贞观（627年-649年）年间易名<b>弥陀寺</b>，<a data-id=\"57c3a8700bd1bea979a0bda5\" data-type=\"entry\" href=\"/detail/57c3a8700bd1bea979a0bda5\" target=\"_blank\">南宋</a><a data-id=\"591adc2f55b5427dfa020b5c\" data-type=\"entry\" href=\"/detail/591adc2f55b5427dfa020b5c\" target=\"_blank\">端平</a>年间(1234一1236年)，荆湖制置使<a data-id=\"57c3a8580bd1be147aa0bda4\" data-type=\"entry\" href=\"/detail/57c3a8580bd1be147aa0bda4\" target=\"_blank\">孟珙</a>为防范金兵南侵，上奏理宗皇帝颁发带金，下诏将<a data-id=\"591059c555b542257a0250fb\" data-type=\"entry\" href=\"/detail/591059c555b542257a0250fb\" target=\"_blank\">随州</a><a data-id=\"592432b855b54278ac018c00\" data-type=\"entry\" href=\"/detail/592432b855b54278ac018c00\" target=\"_blank\">大洪山</a><b>幽济禅寺</b>迁此，改东山为洪山，赐寺名为<b>崇宁万寿掸寺</b>。元末万寿禅寺毁于战火，此后几经毁坏，明<a data-id=\"591adc0e55b5427dfa020860\" data-type=\"entry\" href=\"/detail/591adc0e55b5427dfa020860\" target=\"_blank\">成化</a>二十一年（1485年）定名<b>宝通禅寺</b>。<img class=\"sup-ref\" data-refid=\"ref-1\" data-type=\"sup-ref\" src=\"img/img-reference.png\"/><img class=\"sup-ref\" data-refid=\"ref-2\" data-type=\"sup-ref\" src=\"img/img-reference.png\"/> <img class=\"sup-ref\" data-refid=\"ref-3\" data-type=\"sup-ref\" src=\"img/img-reference.png\"/> <img class=\"sup-ref\" data-refid=\"ref-4\" data-type=\"sup-ref\" src=\"img/img-reference.png\"/></p>\n<p>现存建筑多为<a data-id=\"591adc0c55b5427dfa02083e\" data-type=\"entry\" href=\"/detail/591adc0c55b5427dfa02083e\" target=\"_blank\">光绪</a>年间重建，是历代的皇家寺院，同时也是武汉现存最古老的寺院。寺内有洪山八景（东岩、云扃、怀樽、翠屏、栖霞、狮子峰、仙人石、寿泉），并珍藏着珍贵文物，如宋代古钟为湖北现存佛教文物中最古老的大型冶炼法器，另有<a data-id=\"5924141c55b54278ac00163e\" data-type=\"entry\" href=\"/detail/5924141c55b54278ac00163e\" target=\"_blank\">密宗</a>日式建筑的法界宫，内有飞来巨石，神韵十足<img class=\"sup-ref\" data-refid=\"ref-5\" data-type=\"sup-ref\" src=\"img/img-reference.png\"/>。 寺后的洪山南坡上有<a data-id=\"591acc6755b5427dfa01adb1\" data-type=\"entry\" href=\"/detail/591acc6755b5427dfa01adb1\" target=\"_blank\">洪山宝塔</a>和洪山摩崖石刻，均为湖北省文物保护单位。</p>\n",
      "imageId": "599f9aad1bc9226fdf618c04",
      "imageUrl": "//pic.allhistory.com/T1UBWTByZT1RCvBVdK.jpg",
      "itemWeight": 0.37150782,
      "itemTag": null,
      "disambiguation": "",
      "relations": {
        "direction": "->",
        "id": "5b6150cf2a99a6000155be69",
        "relation": "主持",
        "relationDesc": "<div><a href=\"/detail/5910543755b542257a01cba6\" target=\"_blank\" style=\"font-weight: lighter;\">民国</a>十三年（1924年）春，持松法师回到<a href=\"/detail/591059b855b542257a025025\" target=\"_blank\">武汉</a>，受地方善信之请，出任洪山<a href=\"/detail/591acb0f55b5427dfa018e65\" target=\"_blank\">宝通寺</a>住持。</div>",
        "relationType": "ATTRIBUTION",
        "relationTypeGroup": null,
        "relationWeight": 81,
        "relationId": "5b6150cf2a99a6000155be69",
        "time": {
          "startTime": "1924-00-00 00:00:00",
          "timeDesc": "",
          "endTime": "",
          "startAccuracy": null,
          "startNote": "",
          "endAccuracy": null,
          "endNote": ""
        },
        "position": [{
          "type": "Point",
          "coordinates": [114.299279584089, 30.5960212961461]
        }],
        "positionDesc": "武汉市",
        "properties": null,
        "relationCategoryGroup": null,
        "scoreMachine": null
      },
      "relatedPoint": 1,
      "typePaths": [{
        "name": "文化/古迹",
        "id": "1040"
      }],
      "categoryProp": null,
      "birth": null,
      "death": null,
      "relationList": null,
      "priorRelationTypes": null,
      "workType": null,
      "workIds": null,
      "auditing": false
    }, {
      "id": "5b36f699303a6540ba6d1d95",
      "name": "兴福寺 ",
      "summary": "<p><b>兴福寺</b>又名<b>破山寺</b>、<b>破龙寺</b>、<b>破山兴福寺</b>等，位于<a data-id=\"57eb64f60bd1beac1f8b4567\" data-type=\"entry\" href=\"/detail/57eb64f60bd1beac1f8b4567\"  target=\"_blank\">中国</a><a data-id=\"5910579855b542257a021c42\" data-type=\"entry\" href=\"/detail/5910579855b542257a021c42\"  target=\"_blank\">江苏</a><a data-id=\"591059b555b542257a024ffe\" data-type=\"entry\" href=\"/detail/591059b555b542257a024ffe\"  target=\"_blank\">苏州</a><a data-id=\"591042cb55b542257a00292b\" data-type=\"entry\" href=\"/detail/591042cb55b542257a00292b\"  target=\"_blank\">常熟市</a>北郊、虞山北麓寺路街148号，南临破龙涧，为<a data-id=\"592419b555b54278ac005648\" data-type=\"entry\" href=\"/detail/592419b555b54278ac005648\"  target=\"_blank\">汉族地区佛教全国重点寺院</a>之一。该寺创自<a data-id=\"59104b9b55b542257a010155\" data-type=\"entry\" href=\"/detail/59104b9b55b542257a010155\"  target=\"_blank\">南齐</a>，为邑人郴州刺史倪德光舍宅为寺，初名大慈寺，<a data-id=\"59104b9b55b542257a01014d\" data-type=\"entry\" href=\"/detail/59104b9b55b542257a01014d\"  target=\"_blank\">南梁</a><a data-id=\"591adc2055b5427dfa0209ec\" data-type=\"entry\" href=\"/detail/591adc2055b5427dfa0209ec\"  target=\"_blank\">大同</a>三年（537）改今名<img class=\"sup-ref\" data-refid=\"ref-1\" data-type=\"sup-ref\" src=\"img/img-reference.png\"/>，唐<a data-id=\"591adc2655b5427dfa020a70\" data-type=\"entry\" href=\"/detail/591adc2655b5427dfa020a70\"  target=\"_blank\">咸通</a>九年（868）赐破山兴福寺额。</p><p>寺内现存建筑多为明清时期所建，中轴线上依次为唐尊胜陀罗尼经幢两座（一幢为唐<a data-id=\"591adc2655b5427dfa020a6f\" data-type=\"entry\" href=\"/detail/591adc2655b5427dfa020a6f\"  target=\"_blank\">大中</a>年间造，另一幢据原拓本重建）、龙涧桥与法华桥、山门、天王殿、三佛殿、大雄宝殿和玉佛楼，东侧有白莲池（放生池）、救虎阁、禅堂、四高僧殿、藏经楼和伴竹楼等，西侧有普照堂、斋堂、五观堂、观音殿和文殊殿等，东西有园林，其中东园内有空心潭、空心亭、米碑亭等，西园内有石舫（团瓢）等<img class=\"sup-ref\" data-refid=\"ref-2\" data-type=\"sup-ref\" src=\"img/img-reference.png\"/>，北有塔院。</p>",
      "imageId": "",
      "imageUrl": "",
      "itemWeight": 0.6869,
      "itemTag": null,
      "disambiguation": "常熟市",
      "relations": {
        "direction": "->",
        "id": "5b6150172a99a6000155be55",
        "relation": "主持",
        "relationDesc": "<div><a href=\"/detail/5910543755b542257a01cba6\" target=\"_blank\" style=\"font-weight: lighter;\">民国</a>六年（1917年）冬，月霞法师病重，要应慈法师代他传法于持松。民国七年（1918年）春二月，应慈法师择日在兴福寺升座，代月霞法师传法于持松。<a href=\"/detail/5924a75155b54278ac05f6bb\" target=\"_blank\">持松</a>受法后，继乃师月霞出任虞山<a href=\"/detail/59105c9955b542257a0292fb\" target=\"_blank\">兴福寺</a>住持。</div>",
        "relationType": "ATTRIBUTION",
        "relationTypeGroup": null,
        "relationWeight": 99,
        "relationId": "5b6150172a99a6000155be55",
        "time": {
          "startTime": "1918-00-00 00:00:00",
          "timeDesc": "",
          "endTime": "",
          "startAccuracy": null,
          "startNote": "",
          "endAccuracy": null,
          "endNote": ""
        },
        "position": [{
          "type": "Point",
          "coordinates": [120.740855183193, 31.6434084960435]
        }],
        "positionDesc": "常熟市",
        "properties": null,
        "relationCategoryGroup": null,
        "scoreMachine": null
      },
      "relatedPoint": 1,
      "typePaths": [{
        "name": "文化/古迹",
        "id": "1040"
      }],
      "categoryProp": null,
      "birth": null,
      "death": null,
      "relationList": null,
      "priorRelationTypes": null,
      "workType": null,
      "workIds": null,
      "auditing": false
    }, {
      "id": "59241adf55b54278ac006542",
      "name": "静安寺",
      "summary": "<p>内容正在升级中</p>\n",
      "imageId": "599f9b2e1bc9226fdf61f95b",
      "imageUrl": "//pic.allhistory.com/T1v7EvBCET1RCvBVdK.JPG",
      "itemWeight": 1.4336287,
      "itemTag": null,
      "disambiguation": "",
      "relations": {
        "direction": "->",
        "id": "5b6156932a99a6000155c075",
        "relation": "住持",
        "relationDesc": "<div><a href=\"/detail/5910543755b542257a01cba6\" target=\"_blank\" style=\"font-weight: lighter;\">民国</a>三十四年（1945年）日寇侵华战争失败，无条件投降，持师犹隐居不出。直到民国三十六年（1947年），始应诸方大德之请，出任<a href=\"/detail/58de0d11977fd5ac7afa20fe\" target=\"_blank\">上海</a>名刹<a href=\"/detail/59241adf55b54278ac006542\" target=\"_blank\">静安寺</a>住持，兼静安佛学院院长。</div>",
        "relationType": "ATTRIBUTION",
        "relationTypeGroup": null,
        "relationWeight": 64,
        "relationId": "5b6156932a99a6000155c075",
        "time": {
          "startTime": "1947-00-00 00:00:00",
          "timeDesc": "",
          "endTime": "",
          "startAccuracy": null,
          "startNote": "",
          "endAccuracy": null,
          "endNote": ""
        },
        "position": [{
          "type": "Point",
          "coordinates": [121.488892183088, 31.2253440960841]
        }],
        "positionDesc": "上海市",
        "properties": null,
        "relationCategoryGroup": "HUMAN_THING",
        "scoreMachine": null
      },
      "relatedPoint": 1,
      "typePaths": [{
        "name": "社会生活/生活生产/建筑及场所",
        "id": "3054"
      }],
      "categoryProp": null,
      "birth": null,
      "death": null,
      "relationList": null,
      "priorRelationTypes": null,
      "workType": null,
      "workIds": null,
      "auditing": false
    }, {
      "id": "5910509a55b542257a017958",
      "name": "蔡元培",
      "summary": "<p><b>蔡元培</b>（1868年1月11日－1940年3月5日），字仲申，又字鹤卿、民友、孑民，号寉庼，小名宜哥，小字意可，乳名阿培<sup class=\"sup-reference\" ref-id=\"ref-1\">[1]</sup>，并曾化名蔡振、周子馀，<a data-id=\"5910579855b542257a021c46\" data-type=\"entry\" href=\"/detail/5910579855b542257a021c46\" target=\"_blank\">浙江</a><a data-id=\"591059b855b542257a025020\" data-type=\"entry\" href=\"/detail/591059b855b542257a025020\" target=\"_blank\">绍兴</a><a data-id=\"59241d2455b54278ac008128\" data-type=\"entry\" href=\"/detail/59241d2455b54278ac008128\" target=\"_blank\">山阴县</a>（今浙江<a data-id=\"591059b855b542257a025020\" data-type=\"entry\" href=\"/detail/591059b855b542257a025020\" target=\"_blank\">绍兴</a>）人，近代<a data-id=\"592413d155b54278ac0012f1\" data-type=\"entry\" href=\"/detail/592413d155b54278ac0012f1\" target=\"_blank\">革命</a>家、<a data-id=\"5924127755b54278ac000035\" data-type=\"entry\" href=\"/detail/5924127755b54278ac000035\" target=\"_blank\">教育</a>家、<a data-id=\"592412a155b54278ac000212\" data-type=\"entry\" href=\"/detail/592412a155b54278ac000212\" target=\"_blank\">政治</a>家，也是中国近代<a data-id=\"5924129855b54278ac000171\" data-type=\"entry\" href=\"/detail/5924129855b54278ac000171\" target=\"_blank\">民族学</a>研究的先驱。&nbsp;</p>\n\n<p>他为人宽厚、恻隐为怀，对中国社会及陋俗有透彻观察；两度游学<a data-id=\"57ea3b840bd1be6c4c4dcb3e\" data-type=\"entry\" href=\"/detail/57ea3b840bd1be6c4c4dcb3e\" target=\"_blank\">欧洲</a>、亲炙<a data-id=\"59249e9d55b54278ac058b46\" data-type=\"entry\" href=\"/detail/59249e9d55b54278ac058b46\" target=\"_blank\">文艺复兴人文主义</a>精神及<a data-id=\"57e2261e0bd1be133f524e6f\" data-type=\"entry\" href=\"/detail/57e2261e0bd1be133f524e6f\" target=\"_blank\">法国大革命</a>后的思潮。他把中国文化教育&ldquo;从封建专制时代摆渡到民主自由时代&rdquo;。手定教育方针，创立现代教育制度。把北京大学学术化，奠定中央研究院之基础。倡导<a data-id=\"57ea59750bd1beb3524dcb3f\" data-type=\"entry\" href=\"/detail/57ea59750bd1beb3524dcb3f\" target=\"_blank\">自由思想</a>、民权与<a data-id=\"5924286855b54278ac01132a\" data-type=\"entry\" href=\"/detail/5924286855b54278ac01132a\" target=\"_blank\">女权</a>，致力革除&ldquo;读书为官&rdquo;之旧俗，开<a data-id=\"592412ba55b54278ac0002fa\" data-type=\"entry\" href=\"/detail/592412ba55b54278ac0002fa\" target=\"_blank\">科学</a>性研究风气。</p>\n",
      "imageId": "599f983b1bc9226fdf5f384b",
      "imageUrl": "//pic.allhistory.com/T1rdWvBKAT1RCvBVdK.jpg",
      "itemWeight": 1.6947162,
      "itemTag": null,
      "disambiguation": "",
      "relations": {
        "direction": "<-",
        "id": "5b6154ef2a99a6000155c018",
        "relation": "请教",
        "relationDesc": "<div><div><a href=\"/detail/5910543755b542257a01cba6\" target=\"_blank\" style=\"font-weight: lighter;\">民国</a>十九年（1930年）春，<a href=\"/detail/5924a75155b54278ac05f6bb\" target=\"_blank\">持松法师</a>在汉阳，于<a href=\"/detail/591acb0155b5427dfa018d3f\" target=\"_blank\">归元寺</a>讲<a href=\"/detail/59241d9a55b54278ac00870d\" target=\"_blank\">《楞严经》</a>，学者<a href=\"/detail/5910509a55b542257a017958\" target=\"_blank\">蔡元培</a>曾率学生听讲，向法师请教哲学与宗教大意。</div></div>",
        "relationType": "INFLUENCE",
        "relationTypeGroup": null,
        "relationWeight": 3,
        "relationId": "5b6154ef2a99a6000155c018",
        "time": {
          "startTime": "1930-00-00 00:00:00",
          "timeDesc": "",
          "endTime": "",
          "startAccuracy": null,
          "startNote": "",
          "endAccuracy": null,
          "endNote": ""
        },
        "position": [{
          "type": "Point",
          "coordinates": [114.26514, 30.54979]
        }],
        "positionDesc": "汉阳区",
        "properties": null,
        "relationCategoryGroup": "HUMAN_HUMAN",
        "scoreMachine": null
      },
      "relatedPoint": 1,
      "typePaths": [{
        "name": "政治/政治人物/其他",
        "id": "2915"
      }],
      "categoryProp": null,
      "birth": {
        "startTime": "1868-01-11 00:00:00",
        "timeDesc": "",
        "endTime": null,
        "startAccuracy": "0",
        "startNote": "",
        "endAccuracy": "0",
        "endNote": ""
      },
      "death": {
        "startTime": "1940-03-05 00:00:00",
        "timeDesc": "",
        "endTime": null,
        "startAccuracy": "0",
        "startNote": "",
        "endAccuracy": "0",
        "endNote": ""
      },
      "relationList": null,
      "priorRelationTypes": null,
      "workType": null,
      "workIds": null,
      "auditing": false
    }, {
      "id": "59243c6155b54278ac01dc8a",
      "name": "唐密",
      "summary": "<p><b>唐密</b>，又称<b>真言陀罗尼宗</b>、<b>真言宗</b>、<b>金刚顶宗</b>、<b>毗卢遮那宗</b>、<b>开元宗</b>，佛教<a data-id=\"5924141c55b54278ac00163e\" data-type=\"entry\" href=\"/detail/5924141c55b54278ac00163e\" target=\"_blank\">密宗</a>流派，发源于<a data-id=\"58a67359977fd5765b9fe113\" data-type=\"entry\" href=\"/detail/58a67359977fd5765b9fe113\" target=\"_blank\">印度</a>，在<a data-id=\"57ecbd5c0bd1be7c718b4567\" data-type=\"entry\" href=\"/detail/57ecbd5c0bd1be7c718b4567\" target=\"_blank\">唐玄宗</a>开元年间传入<a data-id=\"57c4ebcc0bd1befc11a0bda3\" data-type=\"entry\" href=\"/detail/57c4ebcc0bd1befc11a0bda3\" target=\"_blank\">汉传佛教</a>中，主要以<a data-id=\"59244bd655b54278ac02937b\" data-type=\"entry\" href=\"/detail/59244bd655b54278ac02937b\" target=\"_blank\">金刚界</a>、<a data-id=\"592443d455b54278ac022a51\" data-type=\"entry\" href=\"/detail/592443d455b54278ac022a51\" target=\"_blank\">胎藏界</a>两部密法为主，称为二部纯密。唐朝之后，<a data-id=\"59244bd655b54278ac02937b\" data-type=\"entry\" href=\"/detail/59244bd655b54278ac02937b\" target=\"_blank\">金刚界</a>、<a data-id=\"592443d455b54278ac022a51\" data-type=\"entry\" href=\"/detail/592443d455b54278ac022a51\" target=\"_blank\">胎藏界</a>两部密法在中国失传，外传至日本，现代日本所传的<a data-id=\"5924279455b54278ac0107b1\" data-type=\"entry\" href=\"/detail/5924279455b54278ac0107b1\" target=\"_blank\">东密</a>、<a data-id=\"592412c455b54278ac000363\" data-type=\"entry\" href=\"/detail/592412c455b54278ac000363\" target=\"_blank\">台密</a>二个流派皆是源自于唐密。</p>\n\n<p>宋代之后，仍有一些属于杂密的密宗修行方式流传，如<a data-id=\"5924601c55b54278ac03bd19\" data-type=\"entry\" href=\"/detail/5924601c55b54278ac03bd19\" target=\"_blank\">蒙山施食</a>、放焰口等，但已不被视为是独立流派。</p>\n",
      "imageId": "599f9b9b1bc9226fdf6259b0",
      "imageUrl": "//pic.allhistory.com/T12NWTByCT1RCvBVdK.jpg",
      "itemWeight": 0.72461164,
      "itemTag": null,
      "disambiguation": "",
      "relations": {
        "direction": "->",
        "id": "5b6159322a99a6000155c102",
        "relation": "复兴",
        "relationDesc": "<div><a href=\"/detail/5924a75155b54278ac05f6bb\" target=\"_blank\" style=\"font-weight: lighter;\">持松法师</a>以赴<a href=\"/detail/57c3f8010bd1be6b05a0bda3\" target=\"_blank\">日本</a>学东密、台密法，返华复兴<a href=\"/detail/59243c6155b54278ac01dc8a\" target=\"_blank\">唐密</a>著称，世称显密圆融大宗师、唐密复兴初祖、贤密初祖。</div>",
        "relationType": "INFLUENCE",
        "relationTypeGroup": null,
        "relationWeight": 2,
        "relationId": "5b6159322a99a6000155c102",
        "time": {
          "startTime": "0000-00-00 00:00:00",
          "timeDesc": "",
          "endTime": "",
          "startAccuracy": null,
          "startNote": "",
          "endAccuracy": null,
          "endNote": ""
        },
        "position": [],
        "positionDesc": "",
        "properties": null,
        "relationCategoryGroup": "HUMAN_THING",
        "scoreMachine": null
      },
      "relatedPoint": 1,
      "typePaths": [{
        "name": "宗教/宗教组织/教派",
        "id": "2909"
      }],
      "categoryProp": null,
      "birth": null,
      "death": null,
      "relationList": null,
      "priorRelationTypes": null,
      "workType": null,
      "workIds": null,
      "auditing": false
    }, {
      "id": "5924285b55b54278ac01128b",
      "name": "萧耀南",
      "summary": "",
      "imageId": "599f9b981bc9226fdf62568a",
      "imageUrl": "//pic.allhistory.com/T1_JWvBmYT1RCvBVdK.jpg",
      "itemWeight": 0.37064388,
      "itemTag": null,
      "disambiguation": "",
      "relations": {
        "direction": "<-",
        "id": "5b6151272a99a6000155bf0e",
        "relation": "结识",
        "relationDesc": "<div><a href=\"/detail/5910543755b542257a01cba6\" target=\"_blank\" style=\"font-weight: lighter;\">民国</a>十三年（1924年）春，<a href=\"/detail/5924a75155b54278ac05f6bb\" target=\"_blank\">持松法师</a>回到<a href=\"/detail/591059b855b542257a025025\" target=\"_blank\">武汉</a>，受地方善信之请，出任洪山<a href=\"/detail/591acb0f55b5427dfa018e65\" target=\"_blank\">宝通寺</a>住持。是年秋季，湖北督军<a href=\"/detail/5924285b55b54278ac01128b\" target=\"_blank\">萧耀南</a>，在宝通寺建仁王护国法会，祈求保国安民，并举行灌顶结缘。</div>",
        "relationType": "INFLUENCE",
        "relationTypeGroup": null,
        "relationWeight": 4,
        "relationId": "5b6151272a99a6000155bf0e",
        "time": {
          "startTime": "1924-00-00 00:00:00",
          "timeDesc": "",
          "endTime": "",
          "startAccuracy": null,
          "startNote": "",
          "endAccuracy": null,
          "endNote": ""
        },
        "position": [{
          "type": "Point",
          "coordinates": [114.299279584089, 30.5960212961461]
        }],
        "positionDesc": "武汉市",
        "properties": null,
        "relationCategoryGroup": "HUMAN_HUMAN",
        "scoreMachine": null
      },
      "relatedPoint": 1,
      "typePaths": [{
        "name": "军事/军事人物",
        "id": "2968"
      }],
      "categoryProp": null,
      "birth": {
        "startTime": "1877-03-00 00:00:00",
        "timeDesc": null,
        "endTime": null,
        "startAccuracy": "0",
        "startNote": "",
        "endAccuracy": "0",
        "endNote": ""
      },
      "death": {
        "startTime": "1926-02-14 00:00:00",
        "timeDesc": null,
        "endTime": null,
        "startAccuracy": "0",
        "startNote": "",
        "endAccuracy": "0",
        "endNote": ""
      },
      "relationList": null,
      "priorRelationTypes": null,
      "workType": null,
      "workIds": null,
      "auditing": false
    }, {
      "id": "5924528455b54278ac02e03d",
      "name": "屈映光",
      "summary": "<p><b>屈映光</b>（1883年2月6日－1973年9月19日），字<b>文六</b>，<a data-id=\"5910579855b542257a021c46\" data-type=\"entry\" href=\"/detail/5910579855b542257a021c46\" target=\"_blank\">浙江省</a><a data-id=\"59242ed955b54278ac015be7\" data-type=\"entry\" href=\"/detail/59242ed955b54278ac015be7\" target=\"_blank\">台州府</a><a data-id=\"591042cb55b542257a002928\" data-type=\"entry\" href=\"/detail/591042cb55b542257a002928\" target=\"_blank\">临海县</a>人，<a data-id=\"582ac88705c3fb234e030571\" data-type=\"entry\" href=\"/detail/582ac88705c3fb234e030571\" target=\"_blank\">清末</a><a data-id=\"5910543755b542257a01cba6\" data-type=\"entry\" href=\"/detail/5910543755b542257a01cba6\" target=\"_blank\">民初</a>政治家、<a data-id=\"57c39acd0bd1be226ea0bda3\" data-type=\"entry\" href=\"/detail/57c39acd0bd1be226ea0bda3\" target=\"_blank\">佛教</a>人物。</p>\n",
      "imageId": "599f9be51bc9226fdf62a092",
      "imageUrl": "//pic.allhistory.com/T1fKWvBXYT1RCvBVdK.jpg",
      "itemWeight": 0.6909786,
      "itemTag": null,
      "disambiguation": "",
      "relations": {
        "direction": "<-",
        "id": "5b6156412a99a6000155c068",
        "relation": "请求",
        "relationDesc": "<div><a href=\"/detail/5910543755b542257a01cba6\" target=\"_blank\" style=\"font-weight: lighter;\">民国</a>二十五年（1936年），<a href=\"/detail/5924a75155b54278ac05f6bb\" target=\"_blank\">持松法师</a>第三次东渡<a href=\"/detail/57c3f8010bd1be6b05a0bda3\" target=\"_blank\">日本</a>回到上海后，驻锡圣仙寺，应菩提学会王一亭、<a href=\"/detail/5924528455b54278ac02e03d\" target=\"_blank\">屈映光</a>诸居士之请，在上海觉园建“丙子息灾法会”。</div>",
        "relationType": "INFLUENCE",
        "relationTypeGroup": null,
        "relationWeight": 62,
        "relationId": "5b6156412a99a6000155c068",
        "time": {
          "startTime": "1936-00-00 00:00:00",
          "timeDesc": "",
          "endTime": "",
          "startAccuracy": null,
          "startNote": "",
          "endAccuracy": null,
          "endNote": ""
        },
        "position": [{
          "type": "Point",
          "coordinates": [121.488892183088, 31.2253440960841]
        }],
        "positionDesc": "上海市",
        "properties": null,
        "relationCategoryGroup": "HUMAN_HUMAN",
        "scoreMachine": null
      },
      "relatedPoint": 1,
      "typePaths": [{
        "name": "军事/军事人物",
        "id": "2968"
      }],
      "categoryProp": null,
      "birth": {
        "startTime": "1883-00-00 00:00:00",
        "timeDesc": null,
        "endTime": null,
        "startAccuracy": "0",
        "startNote": "",
        "endAccuracy": "0",
        "endNote": ""
      },
      "death": {
        "startTime": "1973-09-19 00:00:00",
        "timeDesc": null,
        "endTime": null,
        "startAccuracy": "0",
        "startNote": "",
        "endAccuracy": "0",
        "endNote": ""
      },
      "relationList": null,
      "priorRelationTypes": null,
      "workType": null,
      "workIds": null,
      "auditing": false
    }, {
      "id": "59241d9a55b54278ac00870d",
      "name": "楞严经",
      "summary": "<div class=\"mw-content-ltr\" id=\"mw-content-text\">\n<div class=\"mw-parser-output\">\n<p>《<b>楞严经</b>》（<a data-id=\"5910638255b542257a033c7d\" data-type=\"entry\" href=\"/detail/5910638255b542257a033c7d\" target=\"_blank\">梵文</a>：<span>Śūraṃgama-sūtra</span>），全名《<b>大佛顶如来密因修证了义诸菩萨万行首楞严经</b>》，又名《<b>中印度那烂陀大道场经</b>》，简称《<b>大佛顶首楞严经</b>》、《<b>大佛顶经</b>》、《<b>首楞严经</b>》<sup class=\"sup-reference\" ref-id=\"ref-1\">[1]</sup>，<a data-id=\"5924132455b54278ac0007a5\" data-type=\"entry\" href=\"/detail/5924132455b54278ac0007a5\" target=\"_blank\">大乘佛教</a>经典。据传说，由<a data-id=\"59242fff55b54278ac016a1e\" data-type=\"entry\" href=\"/detail/59242fff55b54278ac016a1e\" target=\"_blank\">般剌密谛</a>在唐朝时传至中国，经怀迪证义，<a data-id=\"592432b655b54278ac018bdf\" data-type=\"entry\" href=\"/detail/592432b655b54278ac018bdf\" target=\"_blank\">房融</a>笔受，译成汉文。<a data-id=\"592417c855b54278ac003fd3\" data-type=\"entry\" href=\"/detail/592417c855b54278ac003fd3\" target=\"_blank\">印顺</a>法师认为它与《<a data-id=\"5924298b55b54278ac0121dd\" data-type=\"entry\" href=\"/detail/5924298b55b54278ac0121dd\" target=\"_blank\">圆觉经</a>》、《<a data-id=\"59242b0055b54278ac01321d\" data-type=\"entry\" href=\"/detail/59242b0055b54278ac01321d\" target=\"_blank\">大乘起信论</a>》属于晚期<a data-id=\"592418e055b54278ac004c22\" data-type=\"entry\" href=\"/detail/592418e055b54278ac004c22\" target=\"_blank\">如来藏</a>真常唯心系的作品。</p>\n\n<p>在明朝与清朝后，《楞严经》长期被<a data-id=\"57c4ebcc0bd1befc11a0bda3\" data-type=\"entry\" href=\"/detail/57c4ebcc0bd1befc11a0bda3\" target=\"_blank\">汉传佛教</a>人士高度推崇，曾有：&ldquo;自从一读楞严后，不看人间糟粕书！<sup class=\"sup-reference\" ref-id=\"ref-2\">[2]</sup>&rdquo;的诗句。《楞严经》梵文原本未传世，从面世开始，因未被列入正式译经目录，对于它的真伪，就有了经久不息的争议，多数汉传佛教信徒皆认同它是佛陀所说，而部分佛教学者认为它是在唐代的中国所写作，再伪托为印度传入的作品。</p>\n</div>\n</div>\n",
      "imageId": "599f9b111bc9226fdf61de6c",
      "imageUrl": "//pic.allhistory.com/T1bRYCByKT1RCvBVdK.png",
      "itemWeight": 1.5123582,
      "itemTag": null,
      "disambiguation": "",
      "relations": {
        "direction": "->",
        "id": "5b614ee92a99a6000155bddc",
        "relation": "听讲",
        "relationDesc": "<div><a href=\"/detail/5910543755b542257a01cba6\" target=\"_blank\" style=\"font-weight: lighter;\">民国</a>十九年（1930年）春，<a href=\"/detail/5924a75155b54278ac05f6bb\" target=\"_blank\">持松法师</a>在汉阳，于归元寺讲<a href=\"/detail/59241d9a55b54278ac00870d\" target=\"_blank\">《楞严经》</a>。</div>",
        "relationType": "EXPERIENCE",
        "relationTypeGroup": null,
        "relationWeight": 63,
        "relationId": "5b614ee92a99a6000155bddc",
        "time": {
          "startTime": "1913-00-00 00:00:00",
          "timeDesc": "",
          "endTime": "",
          "startAccuracy": null,
          "startNote": "",
          "endAccuracy": null,
          "endNote": ""
        },
        "position": [],
        "positionDesc": "",
        "properties": null,
        "relationCategoryGroup": "HUMAN_THING",
        "scoreMachine": null
      },
      "relatedPoint": 1,
      "typePaths": [{
        "name": "宗教/宗教经籍",
        "id": "2920"
      }],
      "categoryProp": null,
      "birth": null,
      "death": null,
      "relationList": null,
      "priorRelationTypes": null,
      "workType": null,
      "workIds": null,
      "auditing": false
    }, {
      "id": "59241d9a55b54278ac00870d",
      "name": "楞严经",
      "summary": "<div class=\"mw-content-ltr\" id=\"mw-content-text\">\n<div class=\"mw-parser-output\">\n<p>《<b>楞严经</b>》（<a data-id=\"5910638255b542257a033c7d\" data-type=\"entry\" href=\"/detail/5910638255b542257a033c7d\" target=\"_blank\">梵文</a>：<span>Śūraṃgama-sūtra</span>），全名《<b>大佛顶如来密因修证了义诸菩萨万行首楞严经</b>》，又名《<b>中印度那烂陀大道场经</b>》，简称《<b>大佛顶首楞严经</b>》、《<b>大佛顶经</b>》、《<b>首楞严经</b>》<sup class=\"sup-reference\" ref-id=\"ref-1\">[1]</sup>，<a data-id=\"5924132455b54278ac0007a5\" data-type=\"entry\" href=\"/detail/5924132455b54278ac0007a5\" target=\"_blank\">大乘佛教</a>经典。据传说，由<a data-id=\"59242fff55b54278ac016a1e\" data-type=\"entry\" href=\"/detail/59242fff55b54278ac016a1e\" target=\"_blank\">般剌密谛</a>在唐朝时传至中国，经怀迪证义，<a data-id=\"592432b655b54278ac018bdf\" data-type=\"entry\" href=\"/detail/592432b655b54278ac018bdf\" target=\"_blank\">房融</a>笔受，译成汉文。<a data-id=\"592417c855b54278ac003fd3\" data-type=\"entry\" href=\"/detail/592417c855b54278ac003fd3\" target=\"_blank\">印顺</a>法师认为它与《<a data-id=\"5924298b55b54278ac0121dd\" data-type=\"entry\" href=\"/detail/5924298b55b54278ac0121dd\" target=\"_blank\">圆觉经</a>》、《<a data-id=\"59242b0055b54278ac01321d\" data-type=\"entry\" href=\"/detail/59242b0055b54278ac01321d\" target=\"_blank\">大乘起信论</a>》属于晚期<a data-id=\"592418e055b54278ac004c22\" data-type=\"entry\" href=\"/detail/592418e055b54278ac004c22\" target=\"_blank\">如来藏</a>真常唯心系的作品。</p>\n\n<p>在明朝与清朝后，《楞严经》长期被<a data-id=\"57c4ebcc0bd1befc11a0bda3\" data-type=\"entry\" href=\"/detail/57c4ebcc0bd1befc11a0bda3\" target=\"_blank\">汉传佛教</a>人士高度推崇，曾有：&ldquo;自从一读楞严后，不看人间糟粕书！<sup class=\"sup-reference\" ref-id=\"ref-2\">[2]</sup>&rdquo;的诗句。《楞严经》梵文原本未传世，从面世开始，因未被列入正式译经目录，对于它的真伪，就有了经久不息的争议，多数汉传佛教信徒皆认同它是佛陀所说，而部分佛教学者认为它是在唐代的中国所写作，再伪托为印度传入的作品。</p>\n</div>\n</div>\n",
      "imageId": "599f9b111bc9226fdf61de6c",
      "imageUrl": "//pic.allhistory.com/T1bRYCByKT1RCvBVdK.png",
      "itemWeight": 1.5123582,
      "itemTag": null,
      "disambiguation": "",
      "relations": {
        "direction": "->",
        "id": "5b6154592a99a6000155c00b",
        "relation": "讲解",
        "relationDesc": "<div><a href=\"/detail/5910543755b542257a01cba6\" target=\"_blank\" style=\"font-weight: lighter;\">民国</a>十九年（1930年）春，<a href=\"/detail/5924a75155b54278ac05f6bb\" target=\"_blank\">持松法师</a>在汉阳，于归元寺讲<a href=\"/detail/59241d9a55b54278ac00870d\" target=\"_blank\">《楞严经》</a>。</div>",
        "relationType": "EXPERIENCE",
        "relationTypeGroup": null,
        "relationWeight": 63,
        "relationId": "5b6154592a99a6000155c00b",
        "time": {
          "startTime": "1930-00-00 00:00:00",
          "timeDesc": "",
          "endTime": "",
          "startAccuracy": null,
          "startNote": "",
          "endAccuracy": null,
          "endNote": ""
        },
        "position": [{
          "type": "Point",
          "coordinates": [114.26514, 30.54979]
        }],
        "positionDesc": "汉阳区",
        "properties": null,
        "relationCategoryGroup": "HUMAN_THING",
        "scoreMachine": null
      },
      "relatedPoint": 1,
      "typePaths": [{
        "name": "宗教/宗教经籍",
        "id": "2920"
      }],
      "categoryProp": null,
      "birth": null,
      "death": null,
      "relationList": null,
      "priorRelationTypes": null,
      "workType": null,
      "workIds": null,
      "auditing": false
    }],
    "priorRelationTypes": ["ATTRIBUTION", "EXPERIENCE", "ACHIEVEMENT", "TEACH", "CAREER", "OTHER", "LOCATION", "INFLUENCE"],
    "workType": null,
    "workIds": null,
    "auditing": false
  },
  "traceReqId": null
}